[
  {
    "text": "916\nव्यास उवाच\nश्रुतं मयैतद् भगवन् दहनं त्रिपुरस्य तु ।\nविचित्रार्थं यथावृत्तं क एवमभिधास्यति ।। १ । ।\nकस्मात् क्रुद्धो नगेन्द्रं तं क्रौञ्चं दारितवान् गुहः ।\nपक्षान् सर्वगिरीन्द्राणां१ कस्माच्चिच्छेद वासवः । ।२ ।\nसनत्कुमार उवाच\nशृणु व्यास महाबुद्धे यन्मां त्वं परिपृच्छसि२ ।\nकुमारेण यथा भिन्नो मैनाकिः३  क्रौञ्चपर्वतः ।।३ ।।\nगिरिराजमथाभ्येत्य मेरुं सर्वसुरालयम् ।\nअपश्यद्वासवः स्कन्दं संघातं तेजसामिव । ।४। ।\nशरस्तम्बवने दृष्ट्वा कुमारमनलप्रभम्४ ।\nसुरराज्यमदाविष्टः शक्रः पप्रच्छ षण्मुखम् । ।५।।\nकस्त्वं दिव्यवपुर्बाल मेरुपर्वतमाश्रितः ।\nन मां पूजयसे दृष्ट्वा देवराजमिहागतम् । ।६। ।\nतमेवं वादिनं शक्रं प्राह शूलधरात्मजः ।\nब्रह्माद्या मां विजानन्ति सिद्धा वेदविदश्च ये । ।७।।\nतपसा लब्धराज्येन न चिरादस्तमेष्यता५ ।\nकिं त्वया जानता शक्र कार्यं किं पूजितेन वा । ।८ । ।\nअथोवाच पुनः शक्रस्तं देव६मनलात्मजम्७ ।\nमत्तः परतरो८ नास्ति मुक्त्वा शर्वपितामहौ ।।९। ।\nकथमेवमवोचस्त्वं९ विबुधाधिपमागतम् ।\nयदि मत्तस्त्वमात्मानं महान्तं मन्यसेनघ । । 8.171.१० ।।\nमैनाकतनयो ह्येष क्रौञ्चसिद्धनिषेवितः१० ।\nसुविस्तीर्णो महाशैलो नैकनिर्झरनिस्रवः । । ११ । ।\nएह्येहि११ त्वं मया सार्धं कुरु शीघ्र प्रदक्षिणम् ।\nय एनमावयोरेकः पूर्वमेव क्रमिष्यति । । १२ । ।\n- - - - - - - - -- - -\n१ सर्वगिरीणां च - ख. । २ पृष्टवानसि - क । ३ मैनाकः - ख. । ४ कुमारं ह्यनलप्रभम् - ख. । ५.. तो - क. ख.  ६ शक्रस्तदेव - क. । ७.. मनलात्मजः - क. । ८ परतरं - ख. । ९ कथं मिथ्य(ा)- मवोचस्त्वं - ख. । १० सिद्धर्षिसेवितः - ख. । ११ एह्येवं - ख ।\n- - - - - - - - -- - -"
  },
  {
    "text": "917\nप्रभावात्तेजसा चैव स महान्नौ भविष्यति ।\nबाढमित्येवमुक्त्वाथ कुमारः१२ षण्मुखस्तदा । । प ३ । ।\nशक्रेण सह संगत्य मयूरवरमास्थितः ।\nमहेन्द्रस्याग्रतो गच्छन् चक्रे क्रौञ्चं प्रदक्षिणम्१३ । । १४। ।\nअथ बुद्ध्वा महेन्द्रस्तु न्यूनमात्मानमानलात् ।\nकुमारमभिसन्धित्सुर्मनसैव प्रदक्षिणम् । । १ ५। ।\nकृत्वा सुनिर्वृतस्तस्थौ उपविष्टः४ शिलातले ।\nजवेनाथ कुमारस्तं क्रौञ्चं कृत्वा प्रदक्षिणम् । ।१ ६। ।\nप्रोवाचेन्द्रं१५ तदा दृष्ट्वा जेताहमिति सत्वरः१६ ।\nअहमेव हि जेतेति शक्रस्तमवदद् गुहम् । । १७। ।\nअसकृद् ब्रुवतोरेवं तयोः शक्रकुमारयोः ।\nक्रौञ्चोभ्येत्य वचः प्राह किमेतदिति भूचरः । । १ ८। ।\nततः शक्र उवाचेदं कुमारं वचनं तदा ।\nएष एवावयोः क्रौञ्चो जयसाक्षी१७ महाबलः । । १ ९। ।\nनानृतं वक्ष्यति ह्येष पौत्रो हिमगिरेर्वरः१८ ।\nपृच्छ्यतां शक्र को दोष इत्याह ज्वलनात्मजः । ।8.171.२ ० । ।\nतं शक्रः सादरं प्राह केन त्वमचलाग्रतः ।\nकृतप्रदक्षिणो१९ ब्रूहि प्रमाणं हि त्वमावयोः । । २१ । ।\nततः क्रौञ्चो विमूढात्मा संचिन्त्य सुचिरं नगः ।\nअयं शचीपतिश्चक्रे मामिहाग्रे प्रदक्षिणम् ।। २ २। ।\n- -२० र्यं प्रहसन्२१ देवानित्युवाच नगाधिपः ।\nअथैवं ब्रुवतस्तस्य सत्यहीनं तदा गिरेः । ।२ ३ । ।\nपपात शिखरं तूर्णं कुलिशेन यथा हतम्२२ ।\nतत्रासन् यानि भूतानि सुराद्यानि गिरीश्वरे ।\nतानि संत्यज्य शीघ्र तं प्रययुः सर्वतो दिशम् । ।२४।।\n- - - - - - - - -- - -\n१२ मयूरे - ख. । १३ क्रौञ्चप्रदक्षिणम, प्रदक्षिणाम् (?) । १४ तस्थावुपविष्टः (?) ' १५ प्रोवाचेदं - क ख. । १६ सद्वचः - ख. । १७ जये साक्षी - ख । १८... र्वच - ख । १९ कृत प्रदक्षिणं - क. ख । २० आहाष्ट्रं - क. । २१ संशय - क- । २२ हतः - क ख ।\n- - - - - - - - -- - -"
  },
  {
    "text": "918\nजहृषे वासवश्चापि मनसा पूजयन् गिरिम् ।\nततश्चुक्रोध रुद्रात्मा गिरेः क्रौञ्चस्य षण्मुखः । ।२५। ।\n- - - - गुहं द्रष्टुं२३ संक्रुद्धं वासवस्तदा ।\nएकस्थे तेजसी पूर्णे वह्निभास्करयोरिव । । (?) २६ ।।\nअथ शक्तिं समुत्क्षिप्य यमानलसमप्रभाम् ।\nचिक्षेप भगवान् स्कन्दः क्रुद्धः क्रौञ्चजिघांसया ।।२७।।\nसा पपात गिरेर्मूर्ध्नि शक्तिः क्रौञ्चस्य सत्वरम् ।\nक्षीणायुषो यथा पुंसो मृत्युपाश - - - - ।।२८।।\nस तया भिन्नमर्मा तु शक्त्या क्रौञ्चो नगोत्तमः२४ ।\nसर्वतश्छिन्नसर्वाङ्गः स्रवद्रुधिरनिर्झरः ।।२९ । ।\nमूर्त्तिमानपतद् भूमौ संज्ञाप्राणविवर्जितः ।\nपतिं विनिहतं दृष्ट्वा पत्न्यस्तस्य सुदुःखिताः । ।8.171.३ ० ।।\nविलपन्त्यस्तदा दीनं२५ पेतुः क्रौञ्चाचलोपरि ।\nमेरुर्हिमाचलो विन्ध्यः कैलासो गन्धमादनः ।।३ १ । ।\nपारियात्रश्च सह्यश्च निषधोदयवामनाः२६ ।\nक्रौञ्चस्य जनकश्चापि मैनाकः पर्वतोत्तमः ।।३ २ ।।\nसर्वे पर्वतराजान२७ आजग्मुः शोकपीडिताः ।\nपरिवार्य गिरिं क्रौञ्चं रुरुदुर्दुःखिता भृशम् । । ३३ ।।\nभ्रातृपुत्र हतं ज्ञात्वा देवदेवी गिरीन्द्रजा ।\nशर्वेण सहिता क्रौञ्चमाजगाम महाव्रता । । ३४। ।\nकुमारेण हतं दृष्ट्वा क्रौञ्चं बान्धवमात्मनः ।\nपीडिताभूत्तदा देवी दृष्ट्वा पितरमर्दितम्२८ । ।३५।।\nहिमवन्तं महाशैलं वधात् पौत्रस्य दुःखितम् ।\nशुशोच गिरिजा दृष्ट्वा मुहुर्वीक्ष्य सुरेश्वरम् ।। ३६ ।।\nभगवन्तमथायातं देव्या सह पिनाकिनम् ।\nशोकेनापि सुसन्तप्ता नमश्चक्रुर्महाबलाः२९ । ।३७। ।\n- - - - - - - - -- - -\n२३ तं क्रुद्धं - क. । २४ क्रौञ्चनगोत्तमः - क. । २५ दीनाः (?) । २६ निषधोदयवामनः - क. । २७ सर्वपर्वतराजान - क. । २८ ... मर्दितुम् क. । २९ मनश्चक्रुर्महमाबलाः - क ।\n- - - - - - - - -- - -"
  },
  {
    "text": "919\nअथ प्रणम्य देवेशं हिमवानचलोत्तमः ।\nव्यज्ञापयत दीनात्मा दुःखशोकपरिप्लुतः ।। ३८ ।।\nशक्रेणानेन भगवन्नात्मानं३० बहुमन्यता ।\nनिधनं नायितः पौत्रो ममायं क्रौञ्चपर्वतः ।।३ ९। ।\nस्पर्धा कास्य कुमारेण तव देव सुतेन हि ।\nनान्तरं वेद यो३१ दर्पात् कुमारस्यात्मनश्च ह । ।8.171.४० ।।\nस्पर्धां कृत्वा कुमारेण हते पौत्रे ममाधुना ।\nनिर्वृतो गतदर्पोयं सुखं तिष्ठतु वासवः । ।४१ । ।\nहते पौत्रे महादेव निमग्नः शोकसागरे ।\nन जीवितुमहं शक्तो यास्ये पौत्रगतिं त्वहम् । ।४२ ।।\nएवं विलपतस्तस्य मेरुविन्ध्यपुरोगमाः ।\nविनेदुर्दुःखसंतप्ता बान्धवाभावपीडिताः ।।४३ ।।\nपितरं दुःखितं दृष्ट्वा तथान्यान् बान्धवान् गिरीन् ।\nअभवच्छोकसन्तप्ता गिरिजापि जगद्धरा ।।४४।।\nअथ तान् दुःखितान् दृष्ट्वा सर्वान् गोवृषवाहनः ।\nमा कार्ष्ट शोकमित्युक्त्वा तनयं प्राह षण्मुखम् ।।४५। ।\nमहान्तस्त्वद्विधाः पुत्र सापराधेपि बान्धवे ।\nनाशुभं कुर्वते कस्मात् क्रौञ्चं निहतवानसि ।।४६।।\nभ्रातृसूनुर्भवन्मातुरेष क्रौञ्चो महागिरिः ।\nकथं भ्रातरमेनं स्वं३२ हतवानसि षण्मुख ।।४७।।\nसदृशं कर्म नैतत्ते३३ मन्मयस्य सुतस्य ते३४ ।\nब्रूहि वा साम्प्रतं कर्म किमत्र बहु मन्यसे ।।४८। ।\nतमेवं वादिनं देवं३५ षण्मुखः पितरं तदा ।\nइदं प्रोवाच सव्रीडं वचनं परमाद्भुतम् । ।४९।।\nशक्रस्यापनयाद्देव क्रौञ्च एष हतो मया ।\nअसन्मन्त्रितवान् यस्माद् विज्ञप्तिमपरां शृणु ।।8.171.५० । ।\n- - - - - - - - -- - -\n३० भगवान् आत्मान - क. । ३१ वेदयन् - क. । ३२ भ्रातरमेवं त्वं (?) । ३३ नैनत्ते - क. । ३४ सुतस्तव -क ।\n- - - - - - - - -- - -"
  },
  {
    "text": "920\nत्वत्प्रसादादहं क्रौञ्चं जीवयामि नगोत्तमम् ।\nदुष्करं नहि मे चिञ्चित् तव देव सुतस्य हि  ।५१ । ।\nउत्तिष्ठेति ततः क्रौञ्चं भ्रातरं प्राह षण्मुखः ।\nस बिभ्रत् पूर्ववद्देहं क्रौञ्चो नगपतिः क्षणात् ।।५२।।\nउत्तस्थौ नीरुजो३६ व्यास आश्चर्यं तदभूत्तदा ।\nजीवितेनाचलेनैवं षण्मुखो वह्निसप्रभः । । ५३ ।।\nस्मरन् रुद्रादधिक्षेपं कोपसंरक्तलोचनः ।\nसमक्षं सर्वदेवानां शक्रस्य च महाबलः । ।५४। ।\nवायुविष्णुयमानां च ब्रह्मणश्च महात्मनः ।\nदेवदेवं३७ प्रणम्येशं पितरं ह्युमया सह । । ५५।।\nबभाषे वचनं देवः कुमारवररूपधृक् ।\nशक्रेणानेन देवेन्द्रा मत्समक्षं प्रभाषितम् । । ५६। ।\nमहांस्त्वत्तोहमित्येव तत्र मां मन्युराविशत् ।\nतन्मयैषा महाशक्तिर्निखाता वसुधातले ।।५७ । ।\nउद्धर्त्तुं योमरः शक्तो मुक्त्वा देवं पिनाकिनम् ।\nउत्पाटयतु स ह्येतां३८ महान्मत्तस्ततो हि सः । ।५८। ।\nएवमुक्त्वा ततो देवो बालार्कसदृशप्रभः ।\nतूष्णीं बभूव हृष्टात्मा तस्थौ च पितृपार्श्वतः ।५९। ।\nअथेन्द्रो देवतामध्ये राज्यदर्पान्वितोमरः३९ ।\nउत्पाटयितुमुत्सेहे तां शक्तिं वसुधां गताम् । ।8.171.६० ।।\nन च चालयितुं शक्तो यत्नादपि सुराधिपः ।\nअथ लज्जान्वितोत्यर्थं तस्माद्देशादपाक्रमत् । ।६१ ।।\nततोन्ये दैवतश्रेष्ठा४० ये यमानिलपुरस्सराः ।\nमतिं चक्रुः समुद्धर्तुं यत्नं शक्त्याश्च दंशिताः (?) ।। ६२ ।।\nन च चालयितुं शेकुस्तां शक्तिममरोत्तमाः ।\nततो विष्णुरमेयात्मा देवान् दृष्ट्वा हतौजसः । ।६३ ।।\n- - - - - - - - -- - -\n३६ निरुजो - क. । ३७ देवी - क. । ३८ सो ह्येता - क. । ३९ राजदर्पान्वितोमरः - क. । ४० देवतेष्ठाः - क. ।\n- - - - - - - - -- - -"
  },
  {
    "text": "921\nशक्तिमुद्धर्तुमुत्सेहे समक्षं त्रिदिवौकसाम् ।\nतेनासौ चाल्यमानापि यस्माच्छक्तिर्धरातले । । ६४। ।\nन चचाल महावीर्या स्कन्दतेजोबलान्विता ।\nततो विष्णुरमेयात्मा ज्ञात्वा तत्त्वार्थमादृतः४१ । । ६५ ।।\nकुमारं पूजयन् भक्त्या शक्त्युत्क्षेपान्न्यवर्तत ।\nअथ सर्वेमरा व्यास विष्णुश्च सुरसत्तमः । ।६६ । ।\nसंस्तुत्य षड्मुख देवमिदमाहुर्महौजसः ।\n- - - - - देवानां महादेवसुतःप्रभुः । । ६७। ।\nनाथः पालयिता स्रष्टा आर्तिघ्नः प्रवरो महान् ।\nत्वया नाथेन देवेश वयं सर्वे सुनिर्वृताः । । ६८। ।\nतिष्ठामः सहिताः सर्वे त्वमस्मान्४२ पाहि सर्वतः ।\nशक्रव्यतिक्रमं चैव बालिश्यान्मोहकारितम् । ।६९। ।\nप्रणयाद्याचितोस्माभिः क्षन्तुमर्हसि सर्वदा ।\nएवं स भगवान् सर्वैः कुमारः संस्तुतोमरैः । ।8.171.७० ।।\nक्रोधं तत्याज शक्रे तु तुतोष च दिवौकसाम् ।\nततस्ते गिरयः सर्वे देवी च हिमवत्सुता । ।७ १ । ।\nदेवराजस्तथा शक्रो हृष्टा गुहमपूजयन् ।\nभगवानपि संतुष्टस्तनयाय वरान् ददौ । ।७२ । ।\nययौ चापि गिरेः शृङ्गं दिव्यं हिमवतः शुभम् ।\nसार्धं गुहेन देव्या च मातॄणां गणनायकः ।।७३ । ।\nक्रौञ्चेन सहिताश्चापि मेरुविन्ध्यादयोचलाः ।\nशक्रश्च सुरराट् देवः स्वानि सद्मानि भेजिरे । ।७४। ।\nएवमेतद्यथा४३ क्रौञ्चः क्रौञ्चसारसवासिनः ।\nगुहेन दारितः शक्त्या पश्चाच्चैव४४ कृतोमरः ३१७५। ।\nदृश्यते चापि४५ तत् क्रौञ्चे क्षतं शक्त्याचलोत्तमे ।\nनैकदैवतसंवासं यदभूद्विस्तृतं४६ महत् ।।७६ ।।\n- - - - - - - - -- - -\n४१. मादितः (?) । ४२ तथास्मान् - क । ४३ एतस्मिन्नन्तरे - घ । ४४ पश्चादुभाभ्यां च - घ. । ४५ दृश्यतेद्यापि (?) । ४६ तदभूद्विस्तृतं - क. ।\n- - - - - - - - -- - -"
  },
  {
    "text": "922\nएतत्ते कथितं सर्वं क्रौञ्चदारणमद्भुतम् ।\nय इमं शृणुयान्मर्त्त्यः सर्वपापैः स मुच्यते४७ । ।७७। ।\nव्यास उवाच\nभगवन्४८ परमेशानो मातॄणां नायकः कथम् ।\nका एता मातरश्चापि शंसैतत् पृच्छतो मम । ।७८।।\nकथं मातृगणा जाताः किन्निमित्तमथापि च ।\nकिंवीर्या किंप्रभावाश्च संभूतास्ते गणाः प्रभो ।।७९।।\nकश्चासामाश्रयो येन वर्तन्ते तद्गणाः शुभाः ।\nकेन मृष्टाः स्वयं वापि एतदिच्छामि वेदितुम् । ।8.171.८० । ।\nसनत्कुमार उवाच\nअत्र४९ ते वर्त्तयिष्यामि मातॄणामुद्भवं शुभम्५० ।\nपुरा हि भगवान् ब्रह्मा सृष्ट्वेमा विविधाः प्रजाः । ।८१ । ।\nअवेक्षमाणः कालेय चचार विबुधेश्वरः ।\nस कदाचित् प्रजाध्यक्षः संध्याकाल उपागते । ।८२।।\nदेशं रम्यं समासाद्य तीरे पूर्वमहोदधेः ।\nरम्ये चकार संध्यां हि वर्षकोटिमतन्द्रितः । ।८३ ।।\nकृतसंध्यस्ततो देवः कमलासनसंस्थितः ।\nचिन्तयामास रम्योयं देशो दृष्टिमनोहरः ।।८४। ।\nकरोम्यत्र५१ पुरं रम्यं सर्वकामसमन्वितम् ।\nइति संचिन्त्य स व्यास भगवान् सर्वसृक् प्रभुः । ।८ ५।।\nतस्मिन् रम्ये प्रदेशे तु चक्रे पुरमनुत्तमम् ।\nलोहितासितसौवर्णैः प्रस्तरैश्चामितप्रभम् ।।८६।।\nअट्टाट्टहासकैश्चैव खातकैश्च समन्वितम् ।\nशृङ्गाटकचतुष्केण चतुष्पादमिव स्थितम् । ।८७।।\n- - - - - - - - -- - -\n४७ प्रमुच्यते -क, अत्रान्तरेध्यायसमाप्तिपुष्पिकावाक्यं दृश्यते घ पुस्तके । ४८ भगवान् - क ख. । ४९ हन्त(?) । ५० इतिहासं पुरातनं - घ. । ५१ आक्राम्यात्र - घ, ।\n- - - - - - - - -- - -"
  },
  {
    "text": "923\nवप्रखातकसंयुक्तैर्गृहैश्चापि५२ महाधनैः५३ ।\nमध्ये मन्दाकिनी वापी सरिद्दिव्या मनोहरा ।।८८ । ।\nनलिनीवनसंछन्ना प्रहृष्टखगनादिता५४ ।\nतत् सृष्ट्वा तु पुरं ब्रह्मा सौवर्णं मणिभूषितम् । ।८९ ।\nप्रोवाच वचनं व्यास परमाद्भुतमर्थवत् ।\nरम्ये पुरवरे येस्मिन् वत्स्यन्ति सुकृताशिनः । ।8.171.९० । ।\nअवध्यास्ते जराहीनास्तेजोबलसमन्विताः ।\nभविष्यन्ति महाभागा मत्प्रसादान्न संशयः ।।९१ ।।\nततः स भगवान्देव उवाच पुनरेव ह ।\nअस्मिन सदैव कामानामिष्टानां सुरसत्तमः । ।९ २। ।\nदेवो वर्षति कोटिं वै तेनास्मिन्५५ सुखिनो जनाः ।\nएवं स भगवानुक्त्वा ब्रह्मा लोकपितामहः ।\nअगच्छत् स्वसभां दिव्यां नैकसिद्धनिषेविताम् ।।९३ । ।\nतस्मिन् गते ततो व्यास असुरैर्दैत्यभाषितैः (?) ।\nअधिष्ठितं पुरं तद्वै सर्वैर्ब्राह्मणकंटकैः । ।९४। ।\nयेषां पतिरसुक्रोधः सर्वशस्त्रभृतां वरः ।\nब्रह्महा यज्ञहा विप्र देवान्तकसुरान्तकः५६ ।।९५।।\nसिंहनादो भीमनादो मद इत्येवमादयः ।\nअथ दैत्याः समागम्य हैमकुण्डपुरस्सराः ।\nतस्मिन्पुरवरे स्थित्वा पीडां५७ चक्रुरनेकशः५८ । ।९६। ।\nद्वेष्टारो जगतस्ते हि जघ्नुर्विप्रान् सहस्रशः ।\nयज्ञहोमादिकाश्छिन्नाः क्रियास्तैरसुराधमैः ।।९७ ।।\nतानेवंकारिणो ज्ञात्वा सर्व एव दिवौकसः ।\nब्रह्मलोकमथाभ्येत्य सर्वमश्रावयन् विभोः  ।९८। ।\nवचो दिवौकसां श्रुत्वा ज्ञात्वा दैत्यविचेष्टितम् ।\nनैतच्छक्यं मयेत्युक्त्वा ब्रह्मा सार्धं सुरोत्तमैः ।।९९। ।\n- - - - - - - - -- - -\n५२ ग्रहैश्चापि - घ. । ५३ ..वरै - घ. । ५४ प्रकृष्टखगनन्दिता - ख. । ५५ तेनास्मि - घ. । ५६ सुरान्तकौ (?) । ५७ क्रीडा (?) । ५८ ... श्चक्रुरनेकशः - क. ।\n- - - - - - - - -- - -"
  },
  {
    "text": "924\nआजगाम भवं द्रष्टुं रम्यं हिमगिरेर्वनम्५९ ।\nयत्र गौरी तपस्तेपे भर्तुं देहार्धधारिणी । । 8.171.१०० । ।\nप्रविष्टास्तत्र ते देवा ब्रह्माद्याः सर्व एव हि ।\nस्त्रिय एवाभवन् तूर्णं पार्वत्यास्तपसो बलात् । ।१ ०१ ।।\nततस्तान् देवदेवेशः स्त्रीभूतान् हि सुरोत्तमान् ।\nकिमर्थमागता यूयमिति पप्रच्छ शूलधृक् । ।१ ०२ । ।\nततस्ते सहिताः सर्वे पूर्वं दैत्यविमर्दनम् ।\nनिवेद्य शम्भवे पश्चात् कृच्छ्रं स्त्रीभावमात्मनः । । १०३ ।।\nयथैवं पुरुषाः पूर्व भवाम इति तेब्रुवन् ।\nतानुवाचाथ देवेशः सुरान् स्त्रीभावमागतान । । १ ०४।।\nयात यूयं सुराः सर्वे स्त्रियो भूत्वासुरान्तिकम् ।\nस्त्रीणामेव हि ते वध्या दानवा बलदर्पिताः । । १० ५।।\nतनूर्मूर्त्तिमतीः कृत्वा परतो मातरः शुभाः ।\nयै६० य एव यथा पूर्वं भविष्यथ सुरोत्तमाः । । १०६ ।।\nअथ भूयः प्रणम्येशं देवता इदमब्रुवन् ।\nआत्मनोपि तनुं देव कुरु मूर्त्तिमतीं स्त्रियम् । । १ ०७। ।\nयया सार्धं बलाद् दैत्यान् हंस्यामः परमेश्वर ।\nततो देवोसृजद्देवीं रूद्राणीं मातरं शुभाम् ।।१ ०८। ।\nविकृतं रूपमास्थाय द्वितीयामपि मातरम् ।\nनाम्ना तु बहुमांसान्तां जगत्संहाररूपिणीम् ।। १० ९। ।\nनियोगाद् देवदेवस्य ततो विष्णुरपि प्रभुः ।\nमातरावसृजद् द्वे तु वाराहीं वैष्णवीमपि ।\nअभूत् पितामहाद् ब्राह्मी शर्वाणी शङ्करादपि । । 8.171.११० । ।\nकौमारी षड्मुखाच्चापि विष्णोरपि च वैष्णवी ।\nवाराही माधवाद् देवी माहेन्द्री च पुरन्दरात् । । १११ । ।\n- - - - - - - - -- - -\n५९ र्वरम् - क. । ६० य - क. ।\n- - - - - - - - -- - -"
  },
  {
    "text": "925\nसर्वतेजोमयो देवी मातॄणां प्रवरा शुभा ।\nबहुमांसा महाविद्या बभूव वृषभध्वजात् । । ११२ । ।\nसर्वासां६१ देवतानां च देहेभ्यो मातरः शुभाः ।\nस्वरूपबलधारिण्यो निर्जग्मुर्दैत्यनाशनाः । । १ रो ३ । ।\nवायव्या६२ वारुणी याम्या कौबेरी च महाबलाः ।\nमहाकाली तथाग्नेयी अन्याश्चैव सहस्रशः । । ११४ । ।\nता गत्वा तत्पुरं रम्यं दैत्यान् भीमपराक्रमान् ।\nजघ्नुर्बहुविधं देव्यो घोरनादैर्विभीषणैः । । ११ ५। ।\nदैत्यहीनं च तच्चक्रुः पुराग्र्यं हेमभूषितम् ।\nअथ दैत्यैर्हतैस्सवैर्देवदेव उमापतिः६३ । । ११६ । ।\nआजगाम प्रदेशं तं मातॄणां वरदित्सया ।\nतान् दृष्टवा निहतान्सर्वान् दैत्यानमरविद्विषः६४ । । १ १७। ।\nपरितुष्टस्तदा तासां वरान्प्रादाद् वृषध्वजः ।\nजगतो मातरो यूयं मातृभूता भविष्यथः । । ११८ । ।\nयुष्माकं ये भविष्यन्ति भक्ताः पुरुषपुंगवाः ।\nस्त्रियौ वापि महाभागा न तान् हिंसन्ति हिंसकाः । । ११ ९। ।\nमृता मम गणाश्चापि भविष्यन्त्यजरामराः ।\nभवतीनामिदं स्थानं कोटीवर्षमिति श्रुतम् । । 8.171.१२० । ।\nभविष्यति जगत्ख्यातं सर्वपापप्रमोचनम् ।\nअहं हेतुर्हि युष्माकं यस्मात् सृष्टा मयैव च । । १२१ । ।\nहेतुकेश्वरनाम्नाहं६५ स्थास्याम्यत्र वरप्रदः ।\nयुष्माभिः सह वत्स्यामि नायकत्वं व्यवस्थितः । । १२२ । ।\nयस्तु युष्मान्मया सार्धं विधिवत् पूजयिष्यति ।\nसर्वपापविमुक्तात्मा स परां गतिमाप्स्यति । । १२३ । ।\nदानवा निहता यस्माच्छूलेन बहुमांसया ।\nशूलकुण्डमिदं नाम्ना ख्यातं तीर्थं भविष्यति । । १ २४। ।\n- - - - - - - - -- - -\n६१-. सर्वेषां क ख ।। ६२ वाथवा (?) । ६३ देवदेवमुमापतिम् - क । ६४ ... विद्विषान् - क. ।\n- - - - - - - - -- - -"
  },
  {
    "text": "926\nइह शूलोदकं पीत्वा बहुमांसां प्रणम्य च ।\nअधृष्यः सर्वहिंस्राणां भविष्यति नरोत्तमः ।। १ २५।।\nप्रतिकूलेति विख्याता रम्या मन्दाकिनी नदी ।\nरुधिरौघवती सेह भवतीनां भविष्यति । । १ २६।।\nअहं ब्रह्मा च विष्णुश्च ऋषयश्च तपोधनाः ।\nमातृतन्त्राणि दिव्यानि मातृयज्ञविधिं परम् । । १ २७।।\nपुण्यानि प्रकरिष्यामो यजनं यैरवाप्स्यथ ।\nब्राह्मं (?) स्वायंभुवं चैव कौमारं यामलं तथा १ २८।।\nसारस्वतं स गान्धारमैशानं नन्दियामलम् ।\nतन्त्राण्येतानि युष्माकं तथान्यानि सहस्रशः । । १२९ । ।\nभविष्यन्ति नरा यैस्तु युष्मान् यक्ष्यन्ति भक्तितः ।\nनराणां यजमानानां वरान् यूयं प्रदास्यथ । ।8.171.१ ३० ।।\nदिव्यसिद्धिप्रदा देव्यो दिव्ययोगा भविष्यथ ।\nयाश्च नार्यः सदा युष्मान् यक्ष्यन्ते सरहस्यतः । । १३१ । ।\nयोगेश्वर्यो भविष्यन्ति रामा दिव्यपराक्रमाः ।\nछगलः कुम्भकर्णश्च मदीयौ गणनायकौ । । १३ २। ।\nयुष्माकं द्वारपालत्वे स्थास्यतस्तौ ममाज्ञया ।\nकोटीवर्षमिदं स्थानं मातॄणां प्रियमुत्तमम् ।। १३३ । ।\nश्मशानं प्रवरं दिव्यं भविष्यति सुखप्रदम् ।\nवरानेवं हि ताँल्लब्ध्वा मातरो लोकमातरः ।। १ ३४। ।\nभक्त्या प्रणम्य देवेशं मुमुदुर्भृशमर्द्दिताः ।\nततःप्रभृति ताः सर्वाः सहिताः शशिमौलिना । । १३ ५। ।\nकोटीवर्षे६६ वसन्ति स्म सर्वलोकाभयप्रदाः६७ ।\nएवं स भगवान् देवो मातॄणां गणनायकः ।\nअभवच्छङ्करो व्यास यन्मां त्वं पृष्टवानसि । । १३ ६। ।\n- - - - - - - - -- - -\n६६ कौटीवर्षं - क. ख. । ६७ सर्वलोकभयप्रदाः - क ।\n- - - - - - - - -- - -"
  },
  {
    "text": "927\nउत्पत्तिमेतां जगतीश्वरीणां६८ ब्रह्मेन्द्रशक्रानिलवन्दितानाम् ।\nपठेन्मनुष्यः शृणुयाच्च नित्यं यः स्वर्गलोकं स मृतो लभेत ।। १ ३७। ।\nइति स्कन्दपुराणे एकसप्तत्यधिकशततमोध्यायः"
  },
  {
    "text": "सनत्कुमार उवाच\nशक्रेण गिरयः पूर्वं छिन्नपक्षा यथा कृताः ।\nतत् प्रवक्ष्यामि ते व्यास शृणु सर्वमशेषतः । ।१ । ।\nपुरा सिंहवपुः कृत्वा विष्णुना परमौजसा ।\nदैत्यदानवनाथे तु हिरण्यकशिपौ हते । ।२ ।।\nप्रह्रादस्तत्सुतो दैत्यो विष्णुं प्रति चुकोप ह ।\nहते पितरि स श्रीमान् महादैत्यपतीश्वरः ।।३ ।।\nबहून्यब्दसहस्राणि चकारोग्रं महातपः ।\nअथ देवश्चतुर्वक्त्रस्तुष्टस्तमसुराधिपम् । ।४। ।\nप्रोवाच स्वयमागत्य वरदोस्मीति सादरम् ।\nप्रणम्योवाच वरदमिदं ब्रह्माणमागतम्१ । ।५ । ।\nप्रह्लादो मन्युतप्ताङ्गः पितुर्वधमनुस्मरन् ।\nभगवन् यदि तुष्टोसि वरदश्च समागतः । ।६।।\nराजानं हतवान् विष्णुः पितरं मम मायया ।\nसंग्रामे तमहं विष्णुं यथा हन्यां तथा कुरु । ।७।।\nतमुवाच ततो ब्रह्मा प्रह्लादमसुरोत्तमम् ।\nअजय्यः समरे विष्णुरवध्यश्च सुरासुरैः ।।८।।\nप्रसादाद्देवदेवस्य जगत्स्रष्टुरुमापतेः ।\nनैष शक्यो मया दातुं वरस्तुभ्यं महासुर । ।९ ।।\n- - - - - - - - -- - -\n६८ जगतीश्वराणां क ।\n१ प्रणम्य तमुवाचेदं वरदं ब्रह्ममागमतम् - क. ।\n- - - - - - - - -- - -"
  },
  {
    "text": "928\nअन्यं वृणु२ यथेष्टं त्वं वरं यावद्ददामि३ ते ।\nचिन्तयित्वा ततो भूयो महाबुद्धिर्महासुरः । । 8.172.१० । ।\nप्रोवाच४ वचनं देवं कमलासनसंस्थितम् ।\nअजय्यो यद्यवध्यश्च स विष्णुर्देवसत्तमः५ । । ११ । ।\nतस्य विष्णोस्ततो देव शक्रस्यान्यस्य वा रिपोः ।\nअवध्योहमजय्यश्च संभवेयं तवाज्ञया । । १२ ।।\nएवस्त्विति तं ब्रह्मा प्रोच्य दानवसत्तम ।\nदिव्यपद्मासनो देवस्तत्रैवान्तरधीयत । । १३ । ।\nप्रह्लादोपि वरं७ लब्ध्वा ब्रह्मणः परमाद्भुतम् ।\nपश्चिमस्योदधेस्तीरे तस्थौ चिन्ताकुलेन्द्रियः । ।१४।।\nकथं हन्यामहं विष्णुं शक्रं चैव शतक्रतुम् ।\nएवं चिन्तयतस्तस्य प्रह्लादस्य सुरद्विषः ।। १ ५।।\nसर्वशैलाधिपः श्रीमाँश्चक्रमन् हिमवान् गिरिः ।\nद्वाभ्यामुत्पत्य पक्षाभ्यामाजगाम वियच्चरः ।। १ ६। ।\nपुरा हि गिरयो व्यास आसन् पक्षसमन्विताः ।\nदिव्या वियद्गमाः सर्वे सर्वलोकचरास्तथा । । १७।।\nतमागतमथो दृष्ट्वा प्रह्रादो हिमवद्गिरिम् ।\nप्राहेदं वचनं प्रीतः कृत्वा स्वागतमादितः ।। १८ ।।\nकश्यपस्य९ वयं पौत्रा दैत्या गिरिवराधिप ।\nभवन्तोपि१० सुतास्तस्य देवा अपि महागिरे११ ।।१ ९। ।\nअस्माकं भवतां चैव एकस्मात् संभवो गिरे१२ ।\nदेवता भ्रातरो१३ भूत्वा अस्माकं देवताश्च१४ हि । ।8.172.२० ।।\nअवमन्यासुरानस्मान् राज्यं कुर्वन्ति दर्पिताः ।\nवयं यूयं च संगत्य जित्वा देवानशेषतः ।\nत्रैलोक्यं सर्वमाक्रम्य राज्यं कुर्मो१५ महागिरे ।।२१ । ।\n- - - - - - - - -- - -\n२ अन्यद् वृणु - क. । ३ वरं दैत्य ददामि - ख, ददानि - क. । ४ उवाच - ख । ५ देवसत्तम - ख. । ६ दानवसत्तमः - क.,. म - ख. । ७ वरान् - ख. । ८ प्रीतो दत्त्वा - क. । ९ कास्यपस्य - क । १० भवतोपि - क ख. । ११ महामुने - क. । १२ मुने - क. । १३ भ्रातरो देवता - क. ख. । १४ देवताञ्च - क. ख. । १५ कुर्म - ख. ।\n- - - - - - - - -- - -"
  },
  {
    "text": "929\nदेवानां१६ यजनं येषु हूयन्ते येषु चाग्नयः ।\nप्रीयन्ते देवता येषु देशाँस्तानचलेश्वर । ।२ २।।\nसहितः सर्वशैलैस्त्वमाक्रम्य त्वरितं जहि ।\nइज्याहीनान् ततो देवान् सुखं हंस्याम निर्वृताः ।। २३ । ।\nइत्युक्तो दैत्यराजेन हिमवानचलोत्तमः ।\nनैतद्युक्तमिति प्राह साशङ्को दानवाधिपम् । ।२४। ।\nपुनरेव ततः प्राह हिमवन्तं महासुरः ।\nमत्तो युक्तं परं१७ त्वं चेद्यदि वेत्सि नगाधिप ।। २५ ।।\nएष त्वां सहितं शैलेर्नेष्यामि निधनं समम् ।\nअप्रमत्तस्तदा तिष्ठ१८ यावत्त्वां हन्मि पर्वत । ।२६ । ।\nदैत्यराजं ततः क्रुद्धं दृष्ट्वा पर्वतसत्तमः ।\nकरोम्येवमिति प्राह ततो दैत्यस्तुतोष सः१९ । । २७।।\nअथ शैलैस्तदा सार्धं हिमवानचलोत्तमः ।\nप्रह्लादस्य वचः श्रुत्वा२० चक्रे देशोपमर्दनम् । ।२८। ।\nपितृदेवात्मिकाः सर्वा यज्ञहोमादिकाः क्रियाः२१ ।\nवर्तन्ते येषु देशेषु गिरयस्तान् समाक्रमन । ।२९ ।।\nअथोत्सन्नेषु देशेषु नारदो मुनिसत्तमः ।\nशक्रायाश्रावयत्२२ सर्वं पर्वतानां व्यतिक्रमम् ।।8.172.३ ० । ।\nतच्छ्रुत्वा क्रोधसन्तप्तो देवराजः शतक्रतुः ।\nसमागम्याचलान् प्राह किमेतदिति मन्युमान् ३१ ।\nअथोचुर्गिरयो व्यास क्रुद्धं देवगणाधिपम् ।\nप्रह्लादस्य भयाद्देव महादैत्यपतेर्वयम् । । ३२ । ।\nइमं व्यतिक्रमं प्राप्ता न२३ दोषो नः कथञ्चन ।\nअथ चेन्मन्यसे दोषमस्माकममराधिप । ।३ ३ ।।\n- - - - - - - - -- - -\n१६ देवतां - क. । १७ वरं - क., युक्तवरं - ख. । १८ ततस्तिष्ठ - ख. । १९ ह - ख. । २० सर्वं - ख. । २१ यज्ञहोमादिकक्रियाः - क. । २२ शक्रमश्रावयत् - क. । २३ ह - ख. ।\n- - - - - - - - -- - -"
  },
  {
    "text": "930\nप्रह्रादान्तिक्रमागच्छ प्रयाम सहिता द्रुतम् ।\nतेनेदं कारितं सर्वं यज्ञदेशोपमर्दनम्२४ ।\nदैत्यराजेन बलिना युष्मदप्रियलिप्सया । ।३ ४। ।\nनापराधोयमस्माकं२५ तथा त्वं विद्धि देवप ।\nतानेव ब्रुवतः शक्रः सुतरां मन्युमान् गिरीन् । । ३५। ।\nपक्षहीनान् तदा चक्रे क्षिप्त्वा वज्रं पुनःपुनः ।\nहीनपक्षास्ततस्ते तु सर्व एवाचलेश्वराः । । ३६ । ।\nपेतुर्महीतले व्यास छिन्नपक्षाः खगा इव ।\nअथ दैत्यपतिः श्रुत्वा प्रह्रादोसुरपुङ्गवः । ।३७।।\nपक्षच्छेदं नगेन्द्राणां भृशं चुक्रोध पीडितः२६ ।\nकिङ्करोमीति संचिन्त्य चिरं दैत्यगणाधिपः । ।३८। ।\nवदर्याश्रममागत्य ददर्श२७ विष्णुमास्थितम् ।\nतस्यासीत् सुमहद्युद्धं विष्णुना सार्धमद्भुतम् ।।३ ९।।\nन शशाक च तं२८ विष्णुर्जेतुं प्रह्लादमोजसा ।\nतयोर्युद्धमभूद् घोरं दिव्यमब्दशतं पुरा ।।8.172.४० ।।\nआत्मानं वेद हीनं च विष्णुः प्रह्लाददानवात् ।\nसोभियुक्तस्तदा युद्धे विष्णुः परमधर्मवित् ।।४१ ।।\nअशक्तो दानवं जेतुं मन्युमानभवत् प्रभुः ।\nअथ ध्यात्वा महादेवं प्रणम्य च पुनः पुनः । ।४२। ।\nसस्मार पर - - - - - - - - - - - ।\n- - - - - - - - - - - - पिनाकिनः । ।४३ । ।\nअवध्यत्वमजय्यत्वं सर्वलोकनिवासिभिः ।\nप्रसादं तमनुस्मृत्य शैवं विष्णुः सुरोत्तमः । ।४४।।\nमहासत्वबलो भूत्वा दैत्यमभ्यद्रवद् बली ।\nहीयमानमथात्मानं हिण्यकशिपोः सुतः । ।४५। ।\n- - - - - - - - -- - -\n२४ देशयज्ञोपमर्दनम् - क. ख । २५ यथास्माकं - क ख । २६ पि(प)ण्डितः - क. । २७ ददृशे - ख. ।\n- - - - - - - - -- - -"
  },
  {
    "text": "931\nज्ञात्वा च बलिनं विष्णुं युद्धदेशादपाक्रमत् ।\nअजितं विष्णुनात्मानं शिवतेजोविमोहितः । ।४६ । ।\nप्रह्रादो जितमात्मानं२९ बुबुधे दानवेश्वरः ।\nब्रह्मणोपि वरं लब्ध्वा अजयय्यत्वमथात्मनः । ।४७।।\nजितमेव तदात्मानममन्यत महासुरः ।\nप्रह्रादासुरसंग्रामं घोरं देवभयंकरम् । ।४८। ।\nअभूदब्दशतं दिव्यं विष्णुना सार्धमद्भुतम् ।\nन श्रुतेन न वीर्येण न शौर्येण न तेजसा । ।४९।।\nन बुद्ध्या न च धर्मेण प्रह्रादसदृशोसुरः ।\nहिरण्यकशिपुर्नासीद्राजा तत्सदृशो महान् । ।8.172.५० । ।\nनान्धको न हिरण्याक्षः प्रह्लादसदृशो बले ।\nभृगुशापात् किलायातो दैत्यत्वं विष्णुरेव सः ।।५१ । ।\nशौर्येण स्पृहयन्ति स्म श्रुतेन विनयेन च ।\nदिवौकसोपि संसिद्धाः प्रह्रादस्य महात्मनः । ।५२। ।\nनाभवंस्तस्य राज्ये तु दुःखशोकान्विताः प्रजाः ।\nएवं स दानवश्रेष्ठः कृत्वा युद्धं तु विष्णुना । ।५३ ।।\nपश्चात्तापोपतप्ताङ्गो विषयेभ्यो गतस्पृहः ।\nवरदानमनित्यं तज् ज्ञात्वा च तपसः फलम् ।।५४। ।\nनिःस्पृहः सर्वकार्येषु विषयेप्साविवर्जितः ।\nसर्वसन्न्यस्तकर्मा तु३० ध्यानाभ्यासपरायणः । ।५६ ।।\nप्रवव्राज महादैत्यः शमेप्सुर्मोक्षसिद्धये ।\nपुनरावर्तकं जन्म बुद्ध्वा चानित्यता पराम् ।।५७। ।\nकष्टं राज्यमिति ज्ञात्वा प्रह्रादः परमार्थवित् ।\nअभिषिच्य सुतं राज्ये दितिजानां३१ विरोचनम् ।।५ ८ ।।\nदैत्यदानवराजानं कृत्वा तमसुरेश्वरम् ।\nमोक्षसिद्धिं परामिच्छन् प्रव्रज्याकृतनिश्चयः । ।५९। ।\n- - - - - - - - -- - -\n२९ जितमित्येव - क. । ३० सन्न्यस्तसर्वकमा तु (?) । ३१ दितिजातां (तं?) - क. ।\n- - - - - - - - -- - -"
  },
  {
    "text": "932\nवरं तत्त्वमथान्वेष्टुं गुणातीतमजं शिवम् ।\nसाक्षाद् भगवतः शिष्यं३२ कपिलस्यासुरिं मुनिम् ।।8.172.६० ।।\nशिष्यत्वेनोपसंगम्य मोक्षविद्यामवाप्तवान्३३ ।\nप्रकृतीनां परं तत्त्वं विकाराणां परं तथा ।। ६१ ।।\nक्षेत्रज्ञं पुरुषं ज्ञात्वा भोक्तारं भोक्तृवर्जितम् ।\nमोक्षविद्यापरार्थज्ञः सांख्यसिद्धान्तपारगः । ।६२ ।।\nसिद्धः पञ्चशिखो नाम्ना सोभवन्मुनिसत्तम३४ ।\nस योगं३५ परमं लब्ध्वा सांख्याचार्यो महामुनिः ।\nदुःखत्रयविनिर्मुक्तः प्राप्तवान् पदमव्ययम् । ।६३ ।।\nश्रीमानेवं त्रिभुवनरिपुर्दैत्यराजो महात्मा\nकृत्वा वैरं विबुधगुरुणा विष्णुना दीर्घकालम् ।\nसिद्धः पश्चाज्जगदभयदः प्राप्तयोगश्च भूत्वा\nमुक्तः पश्चात्३६ स पदममृतं३७ ब्रह्म चाद्यं ह्यवाप । ।६४।।\nक्षेत्रज्ञबोद्धा गुणविप्रयुक्तो३८ दुःखैर्विहीनो भवपाशबन्धैः ।\nतामिस्रमोहप्रतिबन्धमुक्तो३९ योगोश्वरोसौ दितिजाधिपोभूत् ।।६५। ।\nएवं ताँश्छिन्नपक्षाँस्तु गिरीन् सर्वान् पुरन्दरः ।\nप्रचकार मुनिश्रेष्ठ प्राक् पृष्टो यदहं त्वया ।।६ ६।।\nइति स्कन्दपुराणे प्रह्रादचरिते पर्वतपक्षच्छेदोनामा द्विसप्तत्यधिकशततमोध्यायः४०"
  },
  {
    "text": "व्यास उवाच\nनगेन्द्रो जीविते क्रौञ्चे तोषिते च सुरैर्गुहे ।\nयातो१ हिमवतः शृङ्गं पार्वत्या सहितो हरः । ।१ ।।\nकिमन्यदकरोद्देवः किं चैनं प्राह पार्वती ।\nएतत् कथय विप्रेन्द्र न तृप्तिः शृण्वतो हि मे । । २ ।।\n- - - - - - - - -- - -\n३२ सिद्धं - ख । ३  मवाप्नुयात् - क. । ३४ मुनिसत्तमः - क. । ३५ संयोग. - क । ३६ शान्तं - क. । ३७ परममृदुता (?) - ख. । ३८ विप्रमुक्तो - क- । ३९ प्रतिबद्धमुक्तो - ख। । ४०  २२० - ख. । १ तया - क., यात्वा - ष ।\n- - - - - - - - -- - -"
  },
  {
    "text": "933\nसूत उवाच एवमुक्तो मुनीन्द्रेण ब्रह्मणस्तनयोव्ययः ।\nऋषिः परमयोगीशः कथयामास तत्त्वतः । । ३ । ।\nप्रयाते हिमवच्छृङ्गं देवदेवे सहोमया ।\nबभाषे गिरिजा देवं प्रणम्य परमेश्वरम् । ।४। ।\nउञ्छवृत्तेर्हिरण्यस्य२ नैमिशारण्यवासिनः ।\nशौचेन तपसा भक्त्या युक्तस्य च शमेन हि । ।५। ।\nस्वयमेव प्रयाताहं द्विजं पूजां प्रतीच्छितुम् ।\nमाहात्म्यं तस्य तद् दृष्ट्वा ब्राह्मणस्य तपस्विनः । ।६ ।।\nगताहं विस्मयं देव द्विजाः श्रेष्ठतमा इति ।\nदेवेभ्योपि गरीयांसो ब्रह्मणा इति मे मतिः ।\nत्वत्तोथ३ श्रोतुमिच्छामि द्विजमाहात्म्यमुत्तमम् ।।७।।\nदेवदेव उवाच\nएवमेतज्जगद्धात्रि सुरासुरनमस्कृते ।\nश्रेष्ठास्तपस्विनो विप्रा देवेभ्योपि गरीयसः४ । ।८। ।\nमदीया याः प्रजाः५ सृष्टाः६ प्रथमाः प्रभवो ह्यहम् ।\nरुद्रा द्विजातयः पूर्वं मया सृष्टा महौजसः । ।९। ।\nमदीयां मृष्टिमालोक्य ब्रह्मणापि सिसृक्षुणा ।\nब्राह्मणा मूर्धतः सृष्टाः पूर्वमेव महाप्रभाः । । 8.173.१० । ।\nअग्रभूतो७ ह्यहं तेषां द्विजश्रेष्ठस्तदाभवम् ।\nततस्ते८ मत्सखाः९ सर्वे बभूवुर्विप्रसत्तमाः । । ११ ।।\nउत्तमैषापरा१० सृष्टिर्ब्राह्मणाः११ परमेष्ठिनः ।\nधर्मादिकं चतुर्वर्णं सर्वं तेषु प्रतिष्ठितम् ।। १२ । ।\nयज्जुह्वति१२ हविर्विप्रास्तेन तृप्यन्ति देवताः ।\nजगत् प्रतिष्ठितं सर्वं ब्राह्मणानां१३ हि तेजसा । । १३ । ।\n- - - - - - - - -- - -\n२ उञ्छवृत्तिर्हिरण्यस्य - ख टि.  ३ तत्त्व?- - ख. । ४ गरीयांसः (?) । ५ पुरा - क. । ६ सृष्ट्वा - क. । ७ अग्रीभूतो? - क. । ८ ततते - ख । ९ मत्समाः (मन्मयाः) - ख, १० पुरा - ख. । ११ ब्राह्मणं - क । १२ जुह्वन्ति - क. ख. । १३ ब्राह्मण्येन (?) ।\n- - - - - - - - -- - -"
  },
  {
    "text": "934\nमृत्युजन्मापहं यत्तन्मम पाशुपतं व्रतन् ।\nन वर्णाः साधयन्त्यन्ये मुक्त्वा ब्राह्मणसत्तमान् ।।१४। ।\nलक्षणं संप्रवक्ष्यामि द्विजातीनामिदं शृणु ।\nशौचार्जवविधानं च प्रभावं कर्म चैव ह । ।१ ५। ।\nब्राह्मणस्तु भवेज्जात्या१४ संस्काराद् द्विज उच्यते ।\nविद्यया विप्रतां याति ब्राह्मण्यं त्रिविधं स्मृतम् । । १६।।\nयश्च जात्या भवेद् विप्रो यश्च१५ स्याद् वेदपारगः ।\nतयोस्त्राणे वधे चापि१६ पुण्यपापे१७ समे१८ स्मृते१९ ।। १७। ।\nजात्या च यो भवेद्विप्रः सर्वागमविशारदः२० ।\nतपशौचसमायुक्तस्त्र्यवदातः स उच्यते । । १८ । ।\nतादृशं भोजयेच्छ्राद्धे दैवे कर्मणि वापि२१ यः ।\nअक्षयं तद् भवेत् तस्य व्यवदातस्य तर्पणात् ।।१ ९।।\nवेदविद्यो भवेद्विप्रो नित्यं होमपरायणः ।\nसोपि श्रेष्ठः स्मृतो देवि पूजितस्तारयेत् कुलम् ।।8.173.२० ।।\nसर्वथा जातिमात्रेण योपि स्याद् ब्राह्मणः क्वचित् ।\nसोपि लोकगुरुर्देवि पूजितः स्वर्गदो भवेत । ।२ १ । ।\nअग्निहोत्रं तपो यज्ञः शौचमार्जवमेव च ।\nसत्यं वेदप्रसङ्गश्च द्विजकर्म परं स्मृतम् । ।२२ ।।\nनानृतं ब्राह्मणो ब्रूते न हन्ति प्राणिनं द्विजः ।\nन सेवां कुरुते विप्रो न द्विजः पापकृद्भवेत् ।। २३ ।।\nब्राह्मणश्च तपस्वी च न जन्म पुनराप्नुते ।\nविद्वद्ब्राह्मणतां लब्ध्वा किन्न लब्धं हि देहिना२२ । । २४। ।\nमूर्त्तयो याः स्मृता ह्यष्टावर्कसोमादयो मम ।\nसर्वास्ता निवसन्ति स्म ब्राह्मणे तपसैधिते२३ ।।२५।।\n- - - - - - - - -- - -\n१४ भवेज्जन्मात् - क. । १५ यच्च - क. । १६ वापि - ख. । १७ पुण्यपापौ - क ख । १८ समौ - क- ख. । १९ स्मृतौ - क. ख. । २० विदे(व च) विशारदः - ख । २१ चापि - ख । २२ देहिनाम् - ख. । २३ तपमधिते - क. ख. ।\n- - - - - - - - -- - -"
  },
  {
    "text": "935\nद्विजतेजो ह्यवष्टभ्य अमृतं गाव एव च ।\nप्रभवन्ति सदा देवि विप्राः श्रेष्ठतमास्ततः ।।२६।।\nनासाध्यं२४ विद्यते तेषां द्विजानां परमौजसाम् ।\nरुषितास्ते२५ प्रसन्ना वा प्रयच्छन्ति शुभाशुभम् । ।२७।।\nद्विजास्तपस्विनो ये तु वेदविद्याविशारदाः ।\nमुक्तिदास्तु२६ भवेयुस्ते देवानामपि देवताः । ।२८। ।\nअहं पितामहश्चैव तेषां योनिद्वयं२७ स्मृतम् ।\nमत्तः पूर्वं प्रसूतास्ते ततो देवि पितामहात् ।।२९।।\nआवां हेतू द्विजातीनां प्रकृतित्वात् त्वमेव च ।\nप्रकृतिस्त्वं समाख्याता पुरुषः परमो ह्यहम् ।।8.173.३ ० । ।\nब्रह्मविष्णू स्मृतौ यौ तौ रजःसत्वगुणात्मकौ ।\nआवाभ्यां तौ प्रजायेते सृष्टिकाले प्रजापती । ।३१ ।।\nअहं२८ ह्यग्निस्तमो विष्णुः सत्वं ब्रह्मणि संस्थितम् ।\nरजस्त्वं व्यापितं विद्धि गुणभूतेषु कर्मसु ।।३ २।।\nमोहात्मको स्मृतावेतौ तमो रागस्तथैव च ।\nसत्वं नाशयते तौ हि स चाग्नेः२९ संप्रजायते । ।३ ३ ।।\nवह्नितेजाः स्मृता ह्येते महात्मानो द्विजातयः ।\nसर्वतः प्रभवन्त्येते नास्ति तेषां निवारणम् ।। ३४। ।\nआर्जवं समतां चैव विद्धि तेजो द्विजातिषु ।\nतपोविद्यासमायुक्तादार्जवस्तु विशिष्यते ।।३ ५। ।\nअशाठ्यं३० हन्ति पापानि समता मोहबन्धनम् ।\nउभेप्येते निहन्ति स्म आर्जवं सेवितं द्विजैः ।। ३ ६।।\nपुरा भागीरथीतीरे द्विजः परमधर्मवित् ।\nनाम्ना दानरुचिर्नाम उञ्छवृत्तिर्बभूव ह ।।३७। ।\nसर्वविद्याविनीतात्मा सर्वभूताभयप्रदः ।\nसह पत्न्या च मद्भक्तो वह्निहोमपरायणः ।।३८।।\n- - - - - - - - -- - -\n२४ नासाद्यं - ख. । २५ तुषितास्ते - क. । २६ वृत्तिदास्तु - क. । २७ योनीद्वयं - क ख.  । २८ अह - क. । २९ तच्चाग्नेः (?) । ३० असाध्यां - ख. ।\n- - - - - - - - -- - -"
  },
  {
    "text": "936\nअतिथिं भोजयित्वा च३१ पूर्वं देवि यथागतम् ।\nषष्ठे काले ततोश्नाति तस्येदं व्रतमुत्तमम् । ।३ ९ । ।\nअथैवं वर्तमानस्य भूयान् कालो जगाम ह ।\nअतिथावागते३२ तस्य न विकल्पः प्रजायते । ।8.173.४० ।।\nतपशौचसमायुक्त३३ आर्जवैकरतो द्विजः ।\nबभूवात्यर्थमर्चिष्मानर्काग्नी इव३४ तेजसा । ।४१ ।।\nतस्यैवं तपसो३५ वह्निः प्रीतस्तुष्टिमगात् पराम् ।\nशुभदित्सुरभूच्चास्य समीहितफलप्रदः । ।४२ । ।\nकदाचिदथ कालेन षष्ठे काले समागते ।\nहिममेघोल्बणे शीते दुर्दिने पर्यटन् द्विजः । ।४३ ।।\nनापश्यदतिथिं कञ्चिद्३६  बुभुक्षाक्लमखेदितः ।\nयदा नासदितस्तेन दिनान्तेप्यतिथिः क्वचित् । ।४४।।\nअप्राश्यैव तदा किञ्चिदुपवासपरायणः ।\nबभूव द्विजमुख्योसौ नात्मखेदमचिन्तयत्३७ । ।४५।।\nपत्न्यप्यस्य महाभागा पतिभक्तिव्रते रता ।\nयथैवास्याः३८ पतिश्चक्रे तथा साप्यकरोत्तदा ।।४६। ।\nशीतक्षुदुपतप्ताङ्गो नैकद्वन्द्वसमावृतः ।\nक्लेशेन महतातीव खिन्नोभूद्देवि स द्विजः । ।४७।।\nद्वितीयेथ समायाते षष्ठे काले स ह द्विजः३९ ।\nशीतदुर्द्दिनजाद्दोषान्नैवातिथिमवैक्षत४० । ।४८ । ।\nअथाग्निस्तस्य४१ तज्ज्ञात्वा४२ निश्चयं परमं महत् ।\nश्वपाकसदृशं रूपं विकृतं कुत्सितं च हि४३ ।।४९।।\nकृत्वा पादपमूलस्थः४४ प्रददौ तस्य दर्शनम् ।\nक्षुधार्तोथ स विप्रेन्द्रः पर्यटन्नतिथीप्सया । ।8.173.५० । ।\n- - - - - - - - -- - -\n३१ तु - ख । ३२ अतिथेरागमे(?) । ३३ तपसः शौचसंयुक्त - क. ख.। ३४. .नर्काग्न्योरवि(ग्न्योरिव? - ख. । ३५ तप(प्य)तो (?) । ३६ किञ्चिद् - क. । ३७ मन्नखेदमचिन्तयत् - ख. । ३८ यथैव च - ख. । ३९ समागते - क, महाद्विजः - ख. । ४० मवेक्षत - क । ४१ तथाग्निस्तस्य - क. ख । ८२ तं ज्ञात्वा - क. । ४३ बहिः (?) । ४४पादमूलस्थो - क. ख. ।\n- - - - - - - - -- - -"
  },
  {
    "text": "937\nअपश्यद् वृक्षमूलस्थं घोरं विकृतरूपिणम् ।\nश्वपाकं शीतसंखिन्नं नैकव्रणशताङ्कितम्४५ ।।५१ ।।\nदुर्दृशं४६ वृद्धमार्त्तञ्च प्रस्रवत्कृमिशोणितम् ।\nविक्रोशन्तं च तातेति सोपश्यद् द्विजसत्तमः ।।५२ । ।\nकृपणं तमथो दृष्ट्वा श्वपाकं द्विजसत्तमः ।\nसमाश्वसिहि भद्रेति प्रोवाच मधुरं वचः । ।५३ । ।\nशीतापनयनार्थञ्च वह्निमस्यानयद् द्विजः ।\nअथ तं४७ वह्निसंसर्गात् समाश्वस्तमुवाच सः४८ । ।५४।।\nएहि भुंक्ष्वातिथिर्मे त्वं४९ भव भद्रेति सादरम् ।\nतमुवाच ततो५० दीनं५१ श्वपाकस्तपसां निधिम् ।।५५। ।\nश्वपाकोहं द्विजश्रेष्ठ मह्यमन्नमिहैव हि ।\nकुत्सिताय प्रयच्छस्व यथैव मृगपक्षिणाम् ।। ५६ । ।\nनाहं संस्कृतमाहर्तुं योग्योन्नमिति चाब्रवीत् ।\nतमेवं वादिनं ध्यानाज्ज्ञात्वा५२ वह्निमुपस्थितम् । ।५७। ।\nप्रोवाच द्विजशार्दूल इदं वचनकोविदः ।\nनाहं जातिं गर्हयामि पूजयामि .न चानघ । ।५८। ।\nआत्मा सर्वगतो ह्येष सर्वप्राणिषु संस्थितः ।\nआत्मानं तमहं भक्त्या पूजयामि परं शिवम् । ।५९। ।\nसर्वत्र संस्थितं मत्वा पुरुषं परमेश्वरम् ।\nतिर्यक्षु नहि मे कुत्सा त्वद्विधेषु विशेषतः । । 8.173.६० । ।\nसर्वमेव स एवेति तपःशौचपरायणः ।\nपूजयाम्यहमव्यग्रस्तत्र निस्संशयो भव । ।६१ । ।\nकृमिकीटाखुसर्पेषु५३ श्वपाग्देवद्विजातिषु ।\nयदा सर्वगतो ह्यात्मा तदा कुत्सा कथञ्च नः५४ । । ६२ ।।\n- - - - - - - - -- - -\n४५ व्रणशतार्दितम् - ख. । ४६ दुर्दर्श - ख. । ४७ श्वपाकं (?) । ४८ ह - ख । ४९. मंह्य - ख. । ५० तदा - क. । ५१ दीनः - क । ५२ ध्यात्वा ज्ञात्वा - ख. । ५३ क्रिमिकीटाखुसर्पेषु - ख. । ५४ कथञ्चन (?) ।\n- - - - - - - - -- - -"
  },
  {
    "text": "938\nन हि मे कुत्सितो भद्र एहि मे त्वमकुत्सितः५५ ।\nभुंक्ष्व संस्कृतमन्नन्तु प्रापयास्माननुग्रहम् ।। ६३ । ।\nएवमुक्तो द्विजेन्द्रेण श्वपाकः प्रीतिमाँस्तदा ।\nगृहं जगाम विप्रस्य तस्यानुग्रहलिप्सया । । ६४।।\nअथ दानरुचिस्तस्य अतिथेरिव पूजितम् ।\nआतिथ्यं विधिवच्चक्रे भावशुद्धेन चेतसा ।।६५ ।।\nमूर्त्तिमान् सोभवत् प्रीतो भोजितो हव्यवाहनः ।\nप्रददावीप्सितं चास्मै योगैश्वर्यमनुत्तमम् । ।६ ६ ।।\nस योगं परमं प्राप्य उञ्छवृत्तिर्द्विजोत्तमः ।\nविमुक्तः सह पत्न्या तु प्राप्तवानमृतं पदम् । । ६७।।\nयथैव कपिलः सिद्धस्तत्त्ववित् परमो मुनिः ।\nएवमार्जवसंपन्नो ब्राह्मणः कृतलक्षणः ।\nन किञ्चिन्नाप्नुयाद्देवि शुभाच्छुभतरं पदम् । ।६८ ।।\nएतत्ते कथितं नगेन्द्रतनये माहात्म्यमग्र्यं परं\nविप्राणाममरत्विषां सुबहुशः पुण्यायुषः५६ प्रापकम्५७ ।\nशृण्वन्नित्यमिदं पठँश्च विधिवद्विद्वाञ्छुचिर्मानवः\nपुण्यं सौख्यमथायुरीप्सितफलं तेजो बलं चाप्नुयात् । ।६९।।\nमाहात्म्यमेतत् कथितं यथावत्\nमहामहीध्रेन्द्रसुते द्विजानाम् ।\nसृष्टेः प्रभवान्मम ते द्विजेन्द्रा\nमाहात्म्यमित्थं परमं ह्यवापुः । ।8.173.७० । ।\nसनत्कुमार उवाच\nद्विजमाहात्म्यमुल्लिख्य पार्वतीपरमेशयोः ।\nबभूवेत्थं सुसंवादः पुण्यः पापविनाशनः ।।७१ । ।\n- - - - - - - - पाराशर्य तपोधन ।\nश्रोतव्यं मन्यसे मत्तस्तत् पृच्छस्व समाहितः ।।७२। ।\nइति स्कन्दपुराणे द्विजमाहात्म्यवर्णनं नाम त्रिसप्तत्युत्तरशततमोध्यायः५८\n- - - - - - - - -- - -\n५५ त्वा कुत्सितो मया - ख.  ५६ पूर्णायुषः (?) । ५७ पूर्णायुषो ह्या(वा)पकम् - ख. । ५८  २२१ - ख. ।\n- - - - - - - - -- - -"
  },
  {
    "text": "939\nव्यास उवाच भगवन् यत्त्वया प्रोक्तं दक्षयज्ञवधे तदा ।\nप्राप्य पाशुपतं योगं ब्रह्माद्यास्त्रिदिवौकसः१ ।। १ ।।\nलेभिरे परमं तत्त्वं ज्ञानेन हि महामुने ।\nतन्मे कथय भक्ताय शिष्याय परिपृच्छते । ।२ ।।\nकीदृशं तत्परं योगं ज्ञानं पाशुपतं शुभम् ।\nयज्ज्ञात्वा२ ब्राह्मणाः सिद्धाः प्राप्नुयुर्मोक्षमुत्तमम् ।\nइति३ पृष्टस्तु शिष्येण प्रोवाच मुनिसत्तमः ।।३ । ।\nसनत्कुमार उवाच\nसाधु व्यास महाबुद्धे मुमुक्षुरसि पुत्रक ।\nयन्मां पृच्छसि तज्ज्ञानं योगं माहेश्वरं परम् ।।४। ।\nसर्वासां योगविद्यानां यत्तत्त्वं परिकीर्त्यते ।\nसांख्ययोगागमोपेताः सर्वाध्यात्मविशारदाः ।। ५। ।\nयोगैश्वर्यमपि प्राप्य तत्त्वं नैवोपलेभिरे ।\nयदबुद्ध्वा महाभाग ज्ञानं शङ्करभाषितम् ।। ६। ।\nतद्यथा कथितं तेषां त्र्यम्बकेण४ दिवौकसाम् ।\nतत्तेहं संप्रवक्ष्यामि संक्षेपात्तत्त्वनिश्चयम् । ।७। ।\nविस्तरेण न तच्छक्यं वक्तुं वर्षशतैरपि ।\nतस्याहं स्थि?तपक्षन्तु संसारोत्पत्तिनाशनम् । ।८।।\nमुक्तिसिद्धिप्रदं वक्ष्ये संक्षेपान्मतमुत्तमम् ।\nनमस्कृत्य महेशानं पुरुषं भूतभावनम् ।। ९।।\nप्रकृतेः परमं गुह्यं पुद्गलं परमेष्ठिनम् ।\nयं सांख्याः पुरुषं प्राहुः पञ्चविंशमजं विभुम् । । 8.174.१० । ।\nयोगाश्चापि हि षड्विंशं व्यापिनं त्रिगुणात्मकम् (?) ।\nयोसृजत् सृष्टिकाले तु देवौ सर्वजगत्सृजौ ।।१ १ । ।\n- - - - - - - - -- - -\n१ ब्रह्माद्यास्ते दिवौकसः (?) । २ यं ज्ञात्वा - क. ख. । ३ अथ - क. ख. । ४ त्र्यम्बकेण (?) । ५ नमस्कृत्वा - क. ख. । ६ प्रभुः (भुं) - क. ।\n- - - - - - - - -- - -"
  },
  {
    "text": "940\nप्रजापती महात्मानौ ध्यात्वा विष्णुपितामहौ ।\nतं प्रणम्य महादेवं त्र्यक्षं वरदमीश्वरम् । । १२ । ।\nप्रवक्ष्यामि मतं तस्य योगसिद्धान्तनिश्चयम् ।\nलक्षणं विद्धि योगस्य प्रोच्यमानमिदं मया । । १३ । ।\nछिद्यन्ते७ पशुपाशानि यस्याभ्यासान्महामुने ।\nप्रत्ययस्य बहिर्लोपो मनस्यात्मनि संस्थिते । । १ ४। ।\nअभिसन्धिः परे चैव ईश्वरस्यात्मनश्च ह ।\nएष योग इति व्यास कीर्तितः शम्भुना पुरा । । १ ५।।\nभवजन्मापहः सूक्ष्मः प्रपन्नानां दिवौकसाम् ।\nशरीरे तिष्ठतः पुंसो यदात्मनि मनः स्थितम् । । १६ । ।\nअवितर्कं बहिश्चैव सूक्ष्ममभ्यासयोजितम् ।\nकृतानां प्रत्ययैः सूक्ष्मैः सुखदुःखादिसंज्ञिनाम्८ ।। १७। ।\nअशेषलोप इत्यक्त साधकस्य तु युञ्जतः ।\nपरो महेश्वरो देवः सोभिसन्धिस्तु योजकः । ।१ ८ । ।\nअभिसन्धिस्तदा९ यस्मादीश्वरस्यात्मनश्च ह ।\nसुखादानमथैकेन भावना - - योजनात् । । १९। ।\nप्र - - - - - - - - - - तिष्ठतस्सतः ।\nसाधकस्य भवेन्नित्यं ह्यद्रिः (?) सिद्धमिदं फलम् । । 8.174.२० । ।\nअथाधिकरणं तत्र क्रमशः परिकीर्त्यते (?)\nप्रत्याहारमतो१० विद्या प्राणायामस्तथैव च ।\nध्यानञ्च धारणा चैव११ योगाभ्यास उदाहृतः१२ ।।२१ । ।\nतिस्रो मृत्युमतिक्रम्य क्रिया हि चतुरात्मिकाः ।\nवर्त्तन्ते न च वै - - मृत्युः प्रभवते मुने । । २२ ।।\nवश्या हि धातवस्तस्माद् भवन्त्यस्य न संशयः ।\nततोसौ पवमृत्युश्च साधको भवति - - ।। २३ । ।\n- - - - - - - - -- - -\n७ छिद्यन्ति - क. ख । ८ सं व्रतम् - ख । ९ अभिसन्धिस्तु - क, अभिसन्धिस्सा(?), इतः परं पत्रमेकं खण्डितं क पुस्तके । १०.. .स्ततो (।) । ११ धारणाच्चैव - ख । १२ उदाहृतं - ख. ।\n- - - - - - - - -- - -"
  },
  {
    "text": "941\nइमास्तर्क्कक्रिया व्यास मस्तके हृदि चैव हि ।\nअन्तरिक्षे च सर्वास्तु कीर्तिता हि न संशयः । । २४। ।\nस्थानत्रयनिबद्धास्तु चतुर्लक्षणसंस्थिताः ।\nक्रियाः प्रमादिना नैताः शक्याः साधयितुं क्वचित् । । २ ५।।\nतिस्र एताः सदा मृत्युं प्रवृत्ता मोहलक्षणाः ।\nवियोगो न भवेत्तासु क्रियास्वेकैक  - - - । । २६ । ।\nअज्ञानं कम्पते१३ तासु बहिरन्तश्चरास्वपि ।\nक्रियासु१४ साधको युक्तस्तथा मध्यगतासु च । । २७। । भूतेन्द्रियमनःकालदिङ्निवृत्तिः प्रभावतः ।\nदशैवाशास्त्रयः काला१५ भूतानीन्द्रियविस्तरः ।। २८ । ।\nमनःप्रचारसंयुक्तो विषयाभावलक्षणः ।\nप्रत्याहार इति प्रोक्तः पुरा भगवता स्वयम् । । २९ । ।\nदिगन्तरगमाभावात् मनस्यविचलस्थितौ ।\nप्रत्याहारसमुत्पतिर्योगोत्पत्तौ सकृद् भवेत् । । 8.174.३० । ।\nत्रिकालविषयं ज्ञानमैश्वर्योदग्रमेव च ।\nचले मनसि नाभूतां भवेतां संस्थिते१६ समम् । । ३१ ।।\nमनः सर्वमिदं यस्मात् साधनं योगकर्मणः ।\nएकतो मनसः स्थाने तस्माद् यत्नं समाचरेत् । ।३ २ । ।\nप्राणनिग्रहणे१७ ध्यानं प्राणायाममिति स्मृतम ।\nप्राण एव हि वायूनां सारथ्ये वर्तते सदा । ।। ३३ । ।\nप्राणनिग्रहणे योगी नित्यमभ्यासमाचरेत् ।\nउत्तरोत्तरसंसिद्ध्या वायु - - - गोचरे । । ३४। ।\nज्योतिः प्रवर्तनं विद्यान्नित्यमभ्यासयोजितम् ।\nद्विरपाने सकृत्प्राणे समाने च । ' - - - । । ३५ । ।\n- - - र - -) - - ५ - - । - - - ।\n- - - - । - - - ' - - - ' - - - । । ३६ । ।\n- - - - - - - - -- - -\n१३ अज्ञो न कम्पते (?),  प्राज्ञो - (?) । । १४ क्रियातु - ख. । । १५ कालो - ख. । १६ संस्थिता - ख. ।\n- - - - - - - - -- - -\n942\n।।\nकुम्भ एष तृतीयस्तु योगवह्निप्रदीपकः । ।३७। ।\nएभिर्ध्यानगतिः सूक्ष्मा वायुसंरोधकारिता ।\nप्रवर्तते यया योगी परमं वेष्टि पुद्गलम् । । ३ ८।।\nसकृदेव समाहारादसकृत्परिमोक्षणात् ।\nकुम्भकं चैतदुद्दिष्टं१८ प्राणायामादिधारणात् । । ३ ९। ।\nप्राणो वायुरसावात्मा शरीरे जीव - - - ।\nविद्याद् रूपद्वयं तस्य स्थूलं सूक्ष्मं च सर्वतः ।।8.174.४०।।\nअव्यक्तं सूक्ष्मरूपं तु स्थूलमाकारलक्षणम ।\nस्थूलादारभ्य सूक्ष्मं तु ध्यानाभ्यासान्निरूपयेत् १९ ।।४१ । ।\nसूक्ष्मसंरोपणाज्ज्योतिः प्रकाशो जायते मुने ।\nध्यायतः स्थूललक्ष्यं२० तु सर्वदिक्षु सृतं मनः ।\nयदा दीप्तिमदुत्पद्येत् तदाशु स्थापयेत् पुनः ।।४२ । ।\nगिरौ वृक्षे मरुत्पृष्ठे श्वभ्रे प्रासादपंक्तिषु ।\nसमुद्रे वसुधायां वा मनःसंयोगमाचरेत् । ।४३ ।।\nस्थापितं तन्मनस्तत्र पुनः संहारमाव्रजेत् ।\nअचैतन्यं दिशेन्मोहाद् वायुर्दृष्टमतोन्यथा२१ । ।४४। ।\nसंहृत्य च ततो व्यापि भूयो ध्यानगतिं चरेत् ।\nध्यायतो नित्यमभ्यासान्मनो वायु - - - - । ।४५। ।\nप्रवृत्तज्ञानयोगस्य२२ विषयासंगसंक्षये ।\nप्रातिभानि२३ हि विघ्नानि सत्वादिगुणजानि तु ।\nविघ्नभूतानि योगस्य प्रोद्भवन्ति हि युञ्जतः । ।४६।।\nतानि विद्वान् प्रयत्नेन विषयेच्छाविवर्जितः ।\nजित्वा निर्वाणमार्गस्थो भवेत् त्रैगुण्यवर्जितः ।।४७। ।\nआकाशगमनं दिव्यमप्सरोगणसंगजम् ।\nअभिषेकश्च देवेभ्यश्चित्रकाव्यप्रवर्तनम् । ।४८ । ।\n- - - - - - - - -- - -\n१८ कुम्भकमेतदुद्दिष्टं - ख., इतः पूर्व पत्रमेकं खण्डितं क. पुस्तके । १९ - सन्निरूपयेत् - ख. २० लक्षं - ख । २१ दृष्टमतोन्यथा - ख. । २२ ध्यानयोगस्य (?) । २३ प्रतिभा(न्) ति - ख,\n- - - - - - - - -- - -"
  },
  {
    "text": "943\nऐश्वर्यसुखसंसक्तिर्हेमरत्नागमं बहु ।\nसत्वादेतानि विघ्नानि प्रातिभानि तु लक्षयेत् ।।४९।।\nउत्पत्तिमदयुक्तानि२४ भिन्नाचारक्रमाणि तु ।\nरजोविघ्नानि संविद्यात् प्रातिभानि न संशयः । ।8.174.५० ।। क्षयशूलज्वरोन्मादकुष्टसर्पग्रहाणि तु ।\nयातनोद्गमपूर्वाणि तामसानि विनिर्दिशेत् ।।५१। ।\nगुणत्रयसमुत्थानि प्रातिभानि सदा मुनिः ।\nयुञ्जन् संलक्षयेच्छीघ्रं चिकित्सेदाशु चैव हि ।।५२ ।।\nप्राणाद्यानभिसन्धाय२५ मनः संहृत्य चैव हि ।\nप्राणायामेन कुम्भेन हन्याद्विघ्नानि सर्वतः । ।५३ ।।\nरजः सत्वं तमश्चैव प्रधानस्य२६ गुणास्त्रयः ।\nतस्यैव हि महेशस्य प्रजासंसर्गहेतवः ।। ५४।।\nयोगमोहाद् भवन्त्येते साभिमानस्य युञ्जतः ।\nनिरीहो निर्वृतो योगी सचेता घटते यदा । ।५५। ।\nप्रातिभानि तदा यान्ति विघ्नानि हि समं क्षयम् ।\nप्रादुर्भावस्ततस्तेषां गुणानां मोहकारणम् (?) ।।५६ ।।\nतमो रौद्रं विजानीयात् सत्वं ब्रह्मणि संस्थितम् ।\nरजस्तु बैष्णवं विद्यात्तेषां हन्ता२७ महेश्वरः । ।५७। ।\nमहादेवं परं ज्ञात्वा योगाभ्यासरतो द्विजः ।\nगुणत्रयविनिर्मुक्तः शङ्करे लयमाप्नुयात् ।।५८ ।।\nयमैः सनियमैः पूर्वं शोधयेदात्मनस्तनुम् ।\nततः शास्त्रप्रणीतेन धर्माधर्मविवर्जितः२८ ।।५९।।\nक्रमेण सोपदेशेन ध्यानाभ्यासं समाचरेत् ।\nशब्दादीन् विषयान् जित्वा श्रोत्रादीन्द्रियगोचरान्२९ ।।8.174.६० । ।\n- - - - - - - - -- - -\n२४ उन्मत्तमदयुक्तानि - क. । २५ नाभिसंबन्धान् - ख. । २६ प्राधान्यस्य - क., प्राधान्येन(?) । २७ हर्ता - ख. । २८ -धर्मविवर्जितात् - क. । २९ त्वगादिन्द्रियगोचरान् - क. ख. ।\n- - - - - - - - -- - -"
  },
  {
    "text": "944\nसमो दैवततिर्यक्षु३० निर्ममः सर्ववस्तुषु ।\nसर्वारम्भविनिर्मुक्तः पुण्यपापविवर्जितः । ।६ १ । ।\nनिर्द्वन्द्वो३१ निर्जने३२ ईशे योगाभ्यासं समाचरेत् ।\nसाभिमानं सनियमं त्यक्त्वा३३ सांख्यविनिश्चयम् ।। ६२ । ।\nपरे माहेश्वरे योगे नित्यमम्यासमाचरेत् ।\nअष्टौ प्रकृतयो नित्या विकाराश्चैव षोडश । ।६३ ।।\nपुरुषः पञ्चविंशश्च सांख्यसिद्धान्तगोचरः ।\nएतदेव परं गुह्यं३४ द्र्ये सांख्यानां तत्त्वनिश्चये ।\nप्रकृतेरन्तरं ज्ञात्वा पुरुषस्य च मुच्यते३५ । ।६४। ।\nइति स्कन्दपुराणे पाशुपतयोगवर्णनं नाम ध्यानविधौ प्रथमोयं चतुःसप्तत्युत्तरशततमोध्यायः"
  },
  {
    "text": "सनत्कुमार उवाच\nयोगं सांख्यञ्च सर्वत्र द्विविधं ज्ञानमुच्यते ।\nतत्र सांख्यरताः केचित् केचिद् योगपथाश्रिताः १ ।। १ ।।\nअव्यक्तं प्रकृतिश्चैव तथाहङ्कार एव३ च ।\nअष्टौ प्रकृतयो ह्येतास्तन्मात्रः पञ्चभिः सह । । २ । ।\nपञ्च बुद्धीन्द्रियाण्याहुः पञ्च कर्मेन्द्रियाणि च ।\nमनः पञ्च च भूतानि विकाराः षोडश स्मृताः ।।३ ।।\nपुरुषः पञ्चविंशश्च सर्वारम्भविवर्जितः ।\nनित्यः सर्वगतः सूक्ष्मश्चेतावान्४ त्रिगुणेज्झितः । ।४। ।\nसंशुद्धो विमलो भोक्ता अकर्ता साक्षिवत् स्थितः ।\nविदित्वा न विशन्त्येनं भूयः संसारपञ्जरम् ।। ५।।\nपञ्चविंशति तत्त्वानि सांख्यैरेतानि योगिभिः ।\nप्रोक्तानि यद्५ विदित्वा हि मुच्यते किल जन्मनः६ । ।६ । ।\n- - - - - - - - -- - -\n३० देवतातिर्यक्षु - क. ख. । ३१ निर्द्वन्द्वे - क. ख. । ३२ विजने - ख. । ३३ ज्ञात्वा (?) । ३४ ब्रह्म - क.। ३५ मुच्यतीति - क. ।\n१ योगपथे रताः (?),. ग्रताः - क । २ च महांश्चैव () । वे. ..मेव - ख. । ४ श्चैतावान् - क, श्चैत्यवान् (?), ..श्चेतन (?) । ५ यान् - क., ये या - ख. । ६ जन्तवः - क. ।\n- - - - - - - - -- - -"
  },
  {
    "text": "945\n( ९४५) सूक्ष्मा प्रकृतिरव्यक्ता भोज्या७ सर्वरता चला ।\nनित्या चाचेतना चैव विज्ञेया सर्वकामिकी ।।७।।\nतमः सत्वं रजश्चेति८ विषयस्थं गुणत्रयम् ।\nयेषामव्यभिचाराद्धि९ सर्वमेतदवस्थितम् ।।८ ।।\nप्रकाशजननं सत्वं रजः सङ्गप्रवर्तनम् ।\nतमो विमोहनञ्चैव गुणविस्तर उच्यते१० । ।९ । ।\nभिन्नकार्यप्रचाराणामेतेषां गुणसंज्ञिनाम्११ ।\nहेतुना पुरुषार्थेन साधिका वृत्तिरुच्यते१२ । ।8.175.१ ० । ।\nदैवमष्टविभेदन्तु१३ तिर्यक् सप्तविधं स्मृतम् ।\nअविकल्प्यं च मानुष्यं सर्वतेतद्१४ गुणात्मकम् । ।१ १ । ।\nमूढं निश्चेतनं भूतं स्थूलं सूक्ष्ममथापि वा१५ ।\nअमूर्त्तं मूर्त्तिमद्वापि१६ त्रिगुणं सर्वमुच्यते१७ । । १२ । ।\nमोक्षविघ्नकरा ह्येते कीर्तिता योगिनो गुणाः ।\nसक्तस्यैव१८ हि बन्धः स्यादसक्तो मुक्त उच्यते ।\nविभागात् प्रकृतिस्थस्य स्थिता नित्यं गुणत्रयम् (?) ।। १३ । ।\nविभागेन विकारस्था यथाधर्मं समाश्रिताः ।\nभूतसर्गस्त्रिधाभूतः१९ सांख्यज्ञैः परिपठ्यते । । १४ ।\nसंसिद्धः२० प्राकृतश्चैव२१ तथा वैकृत उच्यते२२ ।\nतत्र धर्मेण संसिद्धा योगे माहेश्वरे स्थिताः ।। १ ५। ।\nनेच्छन्ति संभवं व्यास धर्मो (?) पञ्चात्मतः स्मृतः ।\nते पुनर्द्रव्यसंबन्धात् सांख्यदृष्टान्तपण्डिताः । । १ ६।।\nइच्छन्ति२३ कार्यमाश्रित्य कारणाश्रयिणो न हि ।\nप्रधानात् पुरुषाद् बुद्धिरभूत् सत्वाधिकासकृत् ।।१७। ।\n- - - - - - - - -- - -\n७ भोग्या (?) । ८ रजश्चैव - ख. । ९ येषामाद्यविचाराद्धि - ख. । १० मुच्यते - क. ख. । ११ सज्ञिना गुणः - क, । १२ वृत्तिरीरिता - ख. ' १३ विभिन्नन्तु - क ख । १४ सममेतद् - ख । १५ च - ख । १६ भूर्तिमच्चापि - ख. । १७ सर्व त्रिगुणमुच्यते (?) । १ न सक्तस्यैष - क. । १९ स्त्रिधाभूता - ख. । २० संसिद्धं - ख. । २१ प्राकृन्तञ्चैव - ख.  २२ मुच्यते - ख. । २३ इच्छन्ते - ख. ।\n- - - - - - - - -- - -"
  },
  {
    "text": "946\nगुणानां परिणामेन प्राकृतानां जलादिवत्२४ ।\nब्यवसायस्तथा रूपं निश्चयश्चेति भाष्यते । । १८ । ।\nबुद्धिरेव ह्यहङ्कारः प्रत्ययान्तरसंभवात्२५ ।\nमनः केचित् तमिच्छन्ति२६ क्रियाजं गुणसंग्रहम् ।। १९ । ।\nअहमेव हि कर्तेति२७ अहङ्कार उदाहृतः ।\nमनसः कल्पनं वापि२८ स्मृतमिन्द्रियगोचरम् ।\nबुद्धिभूतादहङ्कारात् सत्वोत्पन्नात् प्रकाशिनः ।। 8.175.२० ।।\nबुद्धीन्द्रियाणि जातानि पञ्च सत्त्वोदयानि तु ।\nबोध्यते बुध्यते वापि मुमुक्षुस्त्विन्द्रियैर्यतः२९ । । २१ । ।\nततो बुद्धीन्द्रियाणीति कीर्त्यन्ते तत्त्वचिन्तकैः ।\n- - - - - - - - - - - - - - - - । । २२। ।\nअतः कर्मेन्द्रियाण्याहुर्गुणाज्जातानि राजसात् ।\nतामसादप्यहङ्कारात् तन्मात्राण्यभवन् पुनः ।।२ ३ । ।\nकेचित् सर्वगतान्याहु - - - - - - - - ।\n- - - - विधं तच्च धर्माधर्मसमुद्भवम् ।। २४। ।\nयाति सर्वत्र सिद्धार्थं भूतव्यापि विमोहनम् ।\nशक्तं सर्वाश्रयं सूक्ष्ममनिवारितदिक्पथम् । । २५।।\nलिङ्गः तच्च समाख्यातं देहिनां यच्च कारणम् ।\nयश्च सर्गस्त्रिधा प्रोक्तः स एव नवधा पुनः । । २६।।\nप्राकृतस्य विकारस्य देहभेदाः सहस्रशः ।\nतत्त्वसर्गः स्मृतः पूर्वः३० पिण्डसर्गस्ततोपरः । । २७। ।\nप्रत्ययानां ततः सर्गस्तृतीयः समुदाहृतः ।\nअसक्ति३१ र्विलयस्तुष्टिः सिद्धिश्चेति चतुस्थि - ।।२८।।\nभेदाः प्रत्ययसर्गे तु वैषम्यादपरे स्मृताः ।\nपञ्चाशत् परितो भेदा ये च तेषां गुणा दश । । २९ ।।\n- - - - - - - - -- - -\n२४ जलाद्रिवत् - ख. । २५ प्रयात्यन्तरसंभवात् - ख., .. संभवाम् - ख. । २६ समिच्छन्ति - ख. । २७ तर्केति - ख. । २८ व्यापि - ख. । २९ .. र्युतः - ख. । ३० पूर्वं - ख. । ३१ अशक्ति - ख. ।\n- - - - - - - - -- - -"
  },
  {
    "text": "947\nषष्टिरेते पदार्था हि गीयन्ते कपिलादिभिः ।\nसा तुष्टिर्नवधा भिन्ना सिद्धिश्चैवाष्टधा पुनः ।।8.175.३ ० । ।\nस्मृतः पञ्चविधश्चापि तेषामेव विपर्ययः ।\nअष्टभेदा३२स्त्रिभिन्ना३३ स्याद् दशभिः कार्यबन्धनैः ।।३ १ ।।\nएते षष्टिपदार्थास्तु संख्याज्ञानमिति३४ श्रुतिः ।\nन्यूनामेकाधिकामेके३५ षष्टिमन्ये३६ तु जानते ।।३२।।\nममैव हि पुरा वत्स गुणजे पदपञ्चके ।\nअन्तरं तत्त्वमन्वेष्टुं प्रकृतेः पुरुषस्य च । ।३ ३ ।।\nसांख्यतन्त्रं महद् बुद्ध्वा ज्ञात्वा तत् प्रकृतेः परम् ।\nपचविंशमजं तत्त्वं भोक्तारमभिमानिनम् ।।३४।।\nसन्देहापगमो नाभूदबुद्ध्वा परमेश्वरम् ।\nयदाहं देवदेवेन स्वयमेव जगत्सृजा । ।३ ५। ।\nस्वयोगं शम्भुना वत्स ग्राहितो गतसंशयः ।\nतदा षड्विंशकं तत्त्वं ज्ञात्वा सर्वगमीश्वरम् ।। ३ ६।।\nविमुक्तो योगसंसिद्धौ जातोहं मोहवर्जितः ।\nभोक्ता चेत् प्रकृतेरस्ति भुंक्ते च पुरुषः स्वयम् ।\n- - - - - - - - - - - - नपि द्विज ।।३७।।\nयस्तयोः परतो नित्यम्३७ षड्विंशस्त्वीश्वरो विभुः ।\nतं ज्ञात्वा परमं तत्त्वं मुच्यते जन्मबन्धनात् ।।३८।।\nसांख्यं कृत्स्नमपि ज्ञात्वा गुणान्तरविचारणात् ।\nपञ्चविंशकसंबोधान्नैव मुक्तिः प्रजायते ।\nस बद्धो३८ भोक्तृपाशैस्तु गुणैः प्रकृतिसंभवः । ।३ ९।।\nअभिमानात्मको भोक्ता पुरुषत्वादमोचकः ।\nतं विदित्वापि नैव स्यान्मुक्तिः प्रत्ययवर्जिता । ।8.175.४० ।।\nएष उक्तस्समासेन सांख्यसिद्धान्तविस्तरः ।\nयोगतत्त्वं प्रवक्ष्यामि दुःखजन्मविनाशनम् ।।४१ ।।\n- - - - - - - - -- - -\n३२ भेद (?) । ३३ त्रिभिन्नः (?)  ३४ सांख्या (सांख्य?) ज्ञानमिति - ख. । ३५ ... नेकाधिके - ख. । ३६ रन्ये - ख. । ३७ नित्यं - ख, इतः पूर्व पत्रमेकं खण्डितम् क पुस्तके । ३८ संबन्धो - क. ।\n- - - - - - - - -- - -"
  },
  {
    "text": "948\nसंभवं देहिनश्चैव वैराग्यं येन चोद्भवेत् ।\nधर्माधर्मपरित्यागं३९ सत्यानृतविवर्जितम्४० । ।४२। ।\nयोगाभ्यासं४१ परासङ्गं४२ सूक्ष्मज्ञानमनिन्दितम् ।\nसर्वसंसक्तिनिर्मुक्त४३ मीश्वरप्राप्तिकारणम्४४ । ।४३ । ।\nसिद्धिनिर्द्वन्द्वसंयोगमशुभोदयनाशनम् ।\nपरोपलब्धिविज्ञानं तत्त्वार्थपदनिश्चयम् ।।४४। ।\nभवजन्मापहं योगं विषयेन्द्रियवर्जितम् ।\nमतं पशुपतेः कृत्स्नममृतास्पदलम्भनम् । ।४५ । ।\nइति स्कन्दपुराणे पाशुपतयोगवर्णने ध्यानविधौ द्वितीयोयं पञ्चसप्तत्युत्तरशततमोध्यायः४५"
  },
  {
    "text": "सनत्कुमार उवाच\nउत्पद्यते१ यथा जन्तुर्वैराग्यं व्रजते यथा ।\nयथा प्रबुध्यते चैव तत्ते व्यास वदाम्यहम् ।। १ । ।\nआकाशः२ पवनस्तेजो भूमिरापस्तथैव च ।\nएषामेकत्र संघाताच्छरीरं नाम जायते ।। २। ।\nरसाः सोमात्मकाः सर्वे तथाहारश्चतुर्विधः३ ।\nदेहिनान्तु रसोत्पत्तिराहारस्य निषेवणात्४ । ।३ । ।\nरसाद्रक्तसमुत्पत्तिः शोणितात् पिशितं स्मृतम् ।\nमेद उत्पद्यते मांसात्तस्मादस्थीनि चाभवन् ।।४। ।\nमज्जा चास्थिभवा ज्ञेया ततः शुक्रसमुद्भवः ।\nरक्तशुक्रसमायोगाद् गर्भः५ संभवति स्त्रियाः । ।५ । ।\nऋतुयोगसमाधानाद् दैवकर्मवशादपि ।\nस्त्रियाः पुंसश्च रत्यन्ते द्वावप्येकत्वमागतौ । । ६ ।।\n- - - - - - - - -- - -\n३९ परित्याग - क, परित्याग, (?) । ४० विवर्जिता - ख, विवर्जितः - क । ४१ योगाभ्यासः - (?) । ४२ परासङ्गः - ख-, परासंगः (?) । ४३ संसक्तनिर्मुक्त - ड । ४४ कारणात् - क. । ४५  २२३ - ख. ।"
  },
  {
    "text": "१ उत्पद्यति - कु. । २ आकाशं - ख । ३ तथाहारञ्चतुर्विधम् - क. । ४ निसेवनात् - क. । ५ गर्भं - क. ।\n- - - - - - - - -- - -"
  },
  {
    "text": "949\nतावेकत्वमथापन्नौ प्रेरितौ पवनेन च ।\nकललं त्वेकरात्रेण पञ्चरात्रेण चार्बुदम् । ।७। ।\nपिशितं सप्तरात्रेण मासाच्चाङ्कुरसंभवः ५ ।\nततःप्रभृति गर्भस्य विभागो भवति द्विज । ।८।।\nशिरः पाणिमुखस्कन्धग्रीवापृष्ठादिसंयुतः७ ।\nपञ्चानामथ मासानामक्षिकर्णादिसम्भवः । ।९।।\nसर्वसंपूर्णगात्रस्तु स्रोतोभिर्नवभिर्युतः ।\nव्यक्तीभवति तद्गर्भो मासैरष्टभिरेव तु ।। 8.176.१० । ।\nसंप्राप्ते नवमे मासि सर्वद्रव्यसमन्वितः ।\nपञ्चभूतात्मकं तत्तु चेतोवदवतिष्ठति । । ११ ।।\nगर्भक्लेदेन सिक्ताङ्गः८ सर्वदुःखसमन्वितः९ ।\nजातिं स्मरेद्वसँस्तत्र१० जन्तुः सर्वसमुद्भवाम् । । १२ । ।\nमृतः पुनरहं जातो जातश्चैव पुनर्मृतः ।\nइदानीं जातमात्रस्तु योगमेवाभ्यसाम्यहम् । । १३ ।।\nन पुनर्येन११ संसारं प्रवेक्ष्याम्यशुभोदयम् ।\nएवं चिन्तयतस्तस्य नवमे मासि संगते । । १४।।\nस्वकर्मविनिबद्धस्य जातमात्रस्य देहिनः ।\nदहेमाविशते१२ वायुः स्मृतिमाक्षिप्य तामसः । । १ ५।।\nयेन मूढो निरानन्दो नैवाध्यात्मरतिर्भवेत् ।\nअग्नीषोमात्मकं सर्वं भूतग्रामं चतुर्विधम् । । १ ६। ।\nसंयोगादेवमुत्पन्नमुत्पत्स्यति च सुव्रत ।\nतत्र ये साधुसंपर्काच्छुभकर्मोदयादपि । ।१७। ।\nआगमान्वेषणे सक्ताः पापानुष्ठानवर्जिताः ।\nमत्वा संसारजं क्लेशं१३ जन्ममृत्युभयार्दितम्१४ ।।१ ८ ।।\n- - - - - - - - -- - -\n६ मासादङ्कुरसंभवः - क । ७ ग्रीवपृष्ठादिसंयुत - ?, संयुतम् - क. ख. । ८ सिक्ताङ्गं - क. । ९ समावृतः - क. ख. । १० स्मरति - ख, स्मरन् विसँस्तत्र (?) क, (वि)शेस्तत्र क., संत्रस्तः - (?) । ११ पुनःप्रत्य - ख. । १२ मोहमाविशते (?) - ख । १३ संसारसक्लेश - ख. । १४.. ..भयादितः (?) ।\n- - - - - - - - -- - -"
  },
  {
    "text": "950\nकामक्रोधरतिद्रोहलोभमोहसमावृतम् ।\nवैराग्यं जन्मतः१५ कृत्वा सर्वारम्भपरिक्षयात् ।। १ ९। ।\nअन्विषन्ति१६ शुभार्थं हि गुह्यमध्यात्मदर्शनम् ।\nते योगं परमं प्राप्य ब्रह्म विन्दन्ति तत् परम् । ।8.176.२ ०।।\nतस्य ते संप्रवक्ष्यामि ब्रह्मसंबोधकारणम् ।\nसर्वेषां योगिनां गुह्यं सर्वयोगनिदर्शनम्१७ । ।२१ । ।\nततो माहेश्वरं१८ योगमाख्यास्ये तत्परन्तव१९ ।\nतेजोग्निः कामजो वह्निः क्रोधाग्निर्वीक्षणानलः । ।२२। ।\nजठराग्निश्च भूतात्मा पञ्चैते देहवह्नयः ।\nप्राणापानः समानश्च२० उदानो व्यान एव च । ।२३ ।।\nपञ्चैते वायवो नित्या देहिनो देहसंभवाः२१ ।\nआकाशप्रभवा ह्येते शरीरं चैषु तिष्ठति२२ । ।२४। ।\nमांसरक्तसमाकीर्णं स्नायुमेदोस्थिसंचयम् ।\nत्वचावनद्धं२३ दुर्गन्धं शकृन्मूत्रसमावृतम् ।।२५।।\nतडिदभ्रागमानित्यं मृत्पात्रापातसन्निभम् ।\nसर्वानर्थसमायुक्तं२४  नचिरान्नाशगामि च२५ ।।२६। ।\nएकरूपं नवद्वारं त्रिस्थूणं पञ्चदेवतम् ।\nविषयेन्द्रियसंकीर्णं नैकव्याधिसमार्दितम्२ ६ ।। २७।।\nप्राणादिभिरवष्टब्धं शरीरं यन्त्रवत् स्थितम् ।\nविमुक्तमसकृत्२७ तैस्तु वायुभिर्जीवसंहतैः ।। २८। ।\nआमपात्रमिवापाताच्छीर्यते कालपर्ययात्२८ ।\nपञ्चभूतानि भूतानि देहान्निष्क्रम्य सर्वशः । ।२९। ।\nआविशन्ति तथात्मानमात्मा च विशते द्रुतम् ।\nभूतेषु पवनः श्रेष्ठो जीवस्तद्विनिबन्धनः ।। 8.176.३ ०। ।\n- - - - - - - - -- - -\n१५ जन्मनः (?) - क., जन्मना - ख. । १६ अन्वेषन्ति - ख, अन्विष्यन्ति (?) । १७ सर्वयोगिनि- दर्शनम - क. । १८ विभोर्माहेश्वरं - ख । १९ तत्परन्तपः - क । २० प्राणोपानः समानस्तु - क. ख. । २१ देहसंभवान् - क । २२ तिष्ठते - क. । २३ त्वचावबद्ध - ख. । २४ सर्वानित्यसमायुक्तं - क. ख. । २५ नाशगामिनम् - क. ख । २६ शतार्दितम् - क । २७ वियुक्तमसकृत् (?) । २८ कालपर्यये - ख. ।\n- - - - - - - - -- - -"
  },
  {
    "text": "951\nवाय्वग्नी सहितौ जीवो२९ न जीवः प्राणिनां पृथक् ।\nमूर्तिरन्या न जीवस्य मृत्यौ३० दृश्यति३१ देहिनः ।।३१ ।।\nपञ्चरूपात्परो देवः सूक्ष्मात् सूक्ष्मतरो मतः ।\nनासौ पश्यति न घ्राति न शृणोति न जल्पति । ।३२।।\nन जानाति न च स्पर्शेज्जीवः३२ प्राणसमावृतः३३ ।\nप्राणो नाम महावायुर्जीवं धारयते द्विज ।।३ ३।।\nभासते श्वसते चैव सर्वेष्वपि३५ हि देहिषु ।\nस प्राणो धारयत्यग्निं स च जीव इति स्मृतः । ।३४।।\nवायुसन्धारणो ह्यग्निः क्रियासु परिवर्तते ।\nयो वह्निमानसौ३६ देहे स जीव इति शब्द्यते ।।३ ५।।\nअन्तर्गतो हि भूतानां कर्मारम्भनिबन्धनः३७ ।\nएवमेतच्छरीरन्तु पञ्चभूतगुणात्मकम् । ।३६।।\nतद्विकारे प्रनष्टे३८ तु मृत इत्यभिधीयते ।\nभूतेन्द्रियमनोजीवविषया रागबन्धने (?) ।।३७। ।\nहृदये कर्णिकायां तु मध्यस्थस्तेजसां निधिः ।\nआत्मा सर्वगतो नित्यं वर्जितो विषयादिभिः । ।३८।।\nतिष्ठते स विभुस्तत्र यं विदित्वा विमुच्यते ।\nस येन योगसंसिद्ध्या ध्यानकर्मक्रियाविदा ।।३९।।\nनाडीकर्मसमाधानात् सतताभ्यासयोगतः ।\nभाभिः३९ प्रकाशितो दृष्टो विकारैर्विप्रमोचितः ।।8.176.४० ।।\nदृष्टो भवति विप्रेन्द्र मुक्तिश्चैव ततः स्मृता ।\nषड्विंशकपरिज्ञानाल्लयमाधाय तत्र हि ।।४१ ।।\nसर्वप्राणिगतं सूक्ष्ममात्मदेहे च संस्थितम् ।\nयं प्रपश्यन्ति संसिद्धा योगिनो गतबन्धनाः ।।४२ ।।\n- - - - - - - - -- - -\n२९ जीतो - क. ख. । ३० सृष्टौ (?) । ३१ दृश्येत (?) । ३२ न स्पृशेच्च जीवः (?) । ३३.. स्पर्शं जीवः प्राणसमावृतः - क. । ३४ भाषते - क. । ३५ सर्वेष्वेव - क. । ३६ वह्निर्मानसो - क- ख । ३७ निबन्धनम् - ख. । ३८ तद्विकारप्रनष्टे - ख । ३९ नाभिः - क. ।\n- - - - - - - - -- - -\n952\nयोभ्युपायः परस्तस्य विज्ञानादीश्वरस्य तु ।\nयोगाभ्यासं परं तं ते प्रवक्ष्यामि द्विजोत्तम । ।४३ । ।\nइति स्कन्दपुराणे पाशुपतयोगवर्णने ध्यानविधौ तृतीयः षट्सप्तत्युर४० शततमोध्यायः"
  },
  {
    "text": "सनत्कुमार उवाच\nअन्तरात्मा च १चेतोवान्मनः२ संकल्पजं स्मृतम् ।\nमहाभूतप्रचाराच्च३ क्षोभाग्निर्जोव४ उच्यते । । १।।\nन शरीरं विना चेतस्तच्चेन्५ नास्ति कुतश्च तत् ।\nचेतोपि न विना जीवं स चापि न विना मनः । ।२। ।\nप्राणो जीव इति प्रोक्तः स्पर्शादन्यत् प्रवर्तते ।\nमनः सर्वं निबध्नाति कर्मारम्भमिति७ श्रुतिः ।। ३ ।।\nसर्व एते हि संगत्य८ धारयन्ति शरीरिणम् ।\nयस्य९ चेतोधिकन्तेषां१० स चेतोवान् प्रकीर्तितः । ।४। ।\nचेतसा तु विजानाति शुभाशुभनिबन्धनम् ।\nतन्मनश्चेतसि स्थाप्य नित्याध्यात्मरतिर्भवेत् ।।५। ।\nशब्दादिविषयातीत इन्द्रियाणि निगृह्य तु ।\nध्यानारम्भपरो११ देही स१२ स्यात् कर्मविवर्जितः । ।६। ।\nइन्द्रियाणि न बध्नन्ति मनो देहसमास्थितम् ।\nजीवो बन्धात्मको ज्ञेयः शुभाशुभनिबन्धनात् ।।७। ।\nरजसस्तमसश्चैव गुणयोरशुभात्मनोः ।\nउद्रेकाज्जायते दुःखं सौख्यं सत्वात् प्रजायते । ।८।।\nसौख्यस्य परिणामाद्धि दुःखोत्पत्तिः शरीरिणाम् ।\nजायते च सुखं विप्र भूयो दुःखविपर्ययात् ।।९।।\n- - - - - - - - -- - -\n४० षटषष्ट्युत्तर - क. ।"
  },
  {
    "text": "१ तु - क. । २ मनः - क. । ३ प्रचाराश्च - क. । ४ ... ग्नीजीव - ख. । ५ चेतस्तत्ते - ख. । ६ कुतश्चन - ख. । ७ कर्मभिस्तमिति - ख । ८ एवेति संतत्य - ख. । ९ तस्य - ख. । १० तेषां - क. ख.। ११ मनो - ख. । १२ देहीश - ख. ।\n- - - - - - - - -- - -"
  },
  {
    "text": "953\nएवमन्योन्यसंबद्धं गुणत्रयविकारजम् ।\nसुखदुःखात्मकं मोहं भूतान्याविश्य तिष्ठति । ।8.177.१० ।।\nमनश्चेतःसमाधानाद्विषयोद्विजनादपि१३ ।\nतस्य नाशः समाख्यातः सङ्गस्य च विवर्जनात् ।।१ १। ।\nइच्छानिग्रहणे सक्ताः१४ क्रोधादिपरिवर्जिताः ।\nनिर्ममा निरहङ्कारा बध्यन्ते नैव कर्मभिः । । १ २। ।\nआत्मा सर्वगतो ह्येषः१५ सूक्ष्मः संभोगवर्जितः ।\nयोगिनस्तं प्रपश्यन्ति ध्यानाद्वायुविवर्जनात्१६ ।। १३ । ।\nतावद् भ्रमति संसारे चतुर्योनिषु जन्तुषु ।\nयावन्नात्मानमन्वेष्टि स च विन्नो न जन्म च (?) ।।१४।।\nयद्यपि ध्यानसंसर्गादबुद्ध्वा ब्रह्म नश्यति ।\nतथापि ब्रह्मसायुज्यान्न१७ तु जन्म पुनर्लभेत् । ।१५। ।\nअथैश्वर्यं परं ध्यानाद्योगजं प्राप्नुते मुनिः ।\nविदित्वा परमात्मानं ततो न पुनराव्रजेत् । । १६ ।।\nअसुखान्यपि१८ कर्माणि महापापकृतान्यपि ।\nकृत्वा ध्यानरतो जन्तुस्तरसा नयति क्षयम् । ।१७। ।\nप्राप्य कर्मक्षयं कृत्स्नं ध्यानयुक्त्या१९ महामुने ।\nतिष्ठते निर्भयो योगी परमैश्वर्यसंयुतः । । १८। ।\nकामरोषौ तथा सङ्गो२० द्वेषो रागविनिश्चयः२१ ।\nएते क्षुद्रतरा२२ भावा मुक्त एभिर्विमुच्यते । ।१ ९ । ।\nगर्वो दम्भो२३ ह्यहङ्कारस्तर्को मानोथ मत्सरः ।\nपारुष्यं क्रूरता चैव भावाः क्षत्रनिबन्धनाः२४ । । 8.177.२० । ।\nयस्यैते मोहना न स्युर्विन्दन्त्यात्मानमीश्वरम् ।\nमोहभावान्तरातीतः समदुःखसुखस्सदा ।। २१ । ।\n- - - - - - - - -- - -\n१३ विजनादपि - क. ख., द्वेजनादपि (?) । १४ शक्तिः - क- । १५ योगैः - क. ख- । ५६ वायुर्विवर्जयेत् - क. । १७ ब्रह्मसायुज्यान्न (?) । १८ अभावान्यपि - ख. । १९ ध्यानशक्त्या - क- ख. । २० तथा सङ्गौ - ख. । २१ द्वेषरागविनिश्चयः - क. ख. । २२ शूद्रतरा - क ख. । २३ गर्भस्तम्भो - ख. । २४ क्षात्रनिसबन्धनाः - क. ख. ।\n- - - - - - - - -- - -"
  },
  {
    "text": "954\nनिर्ममत्वादिभिर्युक्तो योगीति परिपठ्यते ।\nयज्ञकर्म समुत्सृज्य वैष्णवं मोहबन्धनम् ।।२२ । ।\nअध्यात्मपरमो नित्यं मुमुक्षुर्ब्राह्मणो भवेत् ।\nत्रिवर्गं संपरित्यज्य योपवर्गे रतिं लभेत्२५ । । २३ ।।\nदिवौकसामसौ२६ पूज्यो विप्र इत्यभिधीयते ।\nध्यानेन क्षीयते कर्म पापं वा यदि वा शुभम् । । २४। ।\nक्षीणकर्मा ततो योगी तत्परं ब्रह्म विन्दति ।\nप्राप्तयोगो मुनिर्ध्यानी यद्यत् कर्तुमभीप्सते२७ । ।२५।।\nतत्तद् भवति तस्याशु मनसा चिन्तितेन वा ।\nयोगिनं पुरुषं दृष्ट्वा पापैर्मुच्यन्ति तत्क्षणात् ।\nयोपि संभाषते तेन२८ सोपि सद्गतिमाप्नुते२९ ।।२६ ।।\nयोगमेव परं३० ज्ञात्वा सर्वाशुभविमोचनम् ।\nसचेतसो द्विजा विप्र बभूवुर्हि मुमुक्षवः । ।२७।।\nध्यानं ध्येयं परं चैव धातारं चैव ये विदुः ।\nतापनात् तपनात् ताप्यान्मुक्तास्ते दुःखबन्धनात् । ।२८। ।\nसर्वारम्भपरित्यागान्ममत्वादिविवर्जनात् ।\nसांख्ययोगागमावेकौ भेदस्तत्वविमोचने३१ । ।२९ ।\nनिर्गुणः सांख्यमुख्यानां पुरुषः परिपठ्यते ।\nदीपनिर्वाणवत्तेषां देहभेदे गतिः स्मृता । । 8.177.३० ।।\nईश्वरः सर्वनिर्मुक्तः क्षेत्रज्ञो योगिनां मतः ।\nपरमैश्वर्यसंयुक्तास्तं विशन्ति हि योगिनः ।।३ १ । ।\nधारणाभिः समं ताभिः३२ प्राणायामैस्तथैव च ।\nआत्मानं योजयेद्यस्तु स यागं लभते परम् । ।३ २। ।\nअहिंसादिसमायुक्तो३३ योगी विगतमत्सरः ।\nध्यानमभ्यसते यस्तु स जयेन्मृत्युजन्मनी । । ३३ । ।\n- - - - - - - - -- - -\n२५ योपवर्गरतो भवेत् (?), योपवर्गरतिर्लभेत् - ख. । २६ दिवौकसामपि - क. ख. । २७ मभीप्सति - क. ख.। २८ योभिसभाषते - ख., संभावितस्तेन - क. ख. । २९. माप्नुयात् - ख. । ३० योगेश्वरपदं - क. । ३१ विमोचनैः - क. । ३२ समन्त्राभिः - क. ख., समस्ताभिः (?) । ३३ अहिंसाभिः समायुक्तो - क. ।\n- - - - - - - - -- - -"
  },
  {
    "text": "955\nनिर्गुणो निरहङ्कारो जितद्वन्द्वोनवग्रहः ।\nभिक्षोपात्तरसाहारो३४ मुमुक्षुरिति शब्द्यते । ।३४।।\nसर्वारम्भसमावस्थः सर्वाश्रयविवर्जितः ।\nकर्ममार्गादतिक्रान्तो ध्यानीति परिकीर्त्यते ।।३ ५। ।\nयस्य नोद्विजते चेतो दुःखापत्तौ३५ महामुने ।\nन हष्यति३६ सुखे चैव ध्यानीति स विशब्दितः । ।३६। ।\nमोक्षसिद्धिप्रदः पन्थास्त्रिविधः परिकीर्तितः ।\nपूर्वः३७ संकेतनः प्रोक्तः पश्चात् संकथनः स्मृतः ।।३७। ।\nसंसक्तश्च तृतीयस्तु तेषां भेदमिमं३८ शृणु ।\nप्रतिरूपं विभोः कृत्वा दशभिर्नियमैर्युतः । ।३८ ।।\nउपास्ते यो मुनिर्ध्यायन् स संकेतन उच्यते ।\nवेदादृतसुखासङ्गः३९ सत्वकर्मा त्वबान्धवान्४० ।।३९।।\nपरित्यज्येश्वरं ध्यायेत्४१ तत्संकथनमुच्यते ।\nसर्वारम्भपरित्यागात् कपिलादिनिषेवितः । ।8.177.४० । ।\nस्मृतः संकथनः पन्था योगाग्निपरिदीपकः ।\nनिर्विकल्पस्तु यत्सर्वं ब्रह्म एवेति पश्यति । ।४१ ।।\nभिन्नसर्वक्रियाचारो ध्यानी संसक्त उच्यते ।\nत्रिविधस्यापि मार्गस्य नियमानियमानि च ।।४२।।\nतान्येव परिकीर्त्यन्ते चर्याभेदा स्त्वनेकधा४२ ।\nत्रयोपि हेतवो मुक्तेरिमे ध्यानपथा मुने । ।४३ ।।\nसम्यगेतान्मुनिर्ज्ञात्वा निर्ममोन्यतमं श्रितः ।\nतदाप्नोति परं ध्यानं येन विन्दति तत्परम् ।।४४। ।\nसर्वान्ध्यानविधीँस्त्वेतानुच्यमानानिमान्मया ।\nशृणु व्यास महाबुद्धे योगैश्वर्यफलप्रदान् । ।४५।।\nइति स्कन्दपुराणे पाशुपतयोगवर्णने ध्यानविधौ चतुर्थः सप्तसप्तत्युत्तर४३ शततमोध्यायः४४\n- - - - - - - - -- - -\n३४ भिक्षावाप्तरसाहारो - क. । ३५ दुखायत्तो - क. । ३६ भविष्यति - क. । ३७ पूर्वं - क.  ३८ भेदमिदं - ख. । ३९ वेदामृ?तसुखासङ्गः - क.,. ..सङ्ग - क. ख. । ४० .. र्मत्सबान्धवान् - क. । ४१ ध्याति - क, ख. । ४२ चर्याभेदस्त्वनेकधा क, । ४३ सप्तषष्ट्युत्तर - क. । ४४  २२५ - ख. ।\n- - - - - - - - -- - -"
  },
  {
    "text": "956\nसनत्कुमार उवाच\nद्विविधं ब्रह्म निर्दिष्टं क्षरमक्षरमेव१ च ।\nविदित्वोभयमेतद्धि मुच्यते सर्वबन्धनैः । । १ । ।\nपञ्चविंशतिमं तत्त्वं क्षरं२ तत् प्रकृतेः परम् ।\nअक्षरं च३ परं ब्रह्म षड्विंशकमिति४ स्मृतम् । ।२ ।।\nमन एकगतं कृत्वा धारणाभिः पुनः पुनः ।\nवायुनिग्रहणं कुर्यात् प्रत्याहारपुरस्सरम् ।। ३ । ।\nमुहूर्तार्धं क्षणं वापि प्रत्याहारं समाचरेत् ।\nतलात् त्रिंशच्छतं चोर्ध्वं प्राणायामनिबन्धनम् । ।४।।\nअभ्यस्तमासनं५ यत् स्यात् स्वस्तिकादि प्रकीर्त्तितम् ।\nतद् बद्ध्वा विजने देशे ध्यानाभ्यासं समाचरेत् ।।५।।\nक्षुधार्त्तो वातिभुक्तो वा रुजा दुःखान्वितोपि वा ।\nन ध्यायीत पुनर्विद्वान् य इच्छेद् ध्यानमात्मनः । ।६ । ।\nयोगहस्तं ततः कृत्वा वामस्योपरि दक्षिणम् ।\nअधोमुखो भवेत् किञ्चित् पश्यन्नासाग्रमात्मनः । ।७।।\nअस्पृशन् दशनैर्दन्तानोङ्कारं ब्रह्म संस्मरन् ।\nध्यायीत निर्ममो६ विद्वान प्राणायामपुरःसरम् । ।८।।\nआत्मानमात्मना योज्य सर्वाङ्गानि तु संहरेत् ।\nनिरीहः पिहिताक्षश्च७ निक्षिप्य हृदि धारणाम् । ।९। ।\nपाषाण इव निष्पन्दो मुनिर्ध्यानं समाचरेत् ।\nएकत्रास्पन्दसन्धानं मनसो८ धारणा स्मृता ।। 8.178.१० ।।\nएवं प्रतिदिनं तस्य ध्यायतो योगिनो मुने ।\nविकारा गुणजाः सर्वे नश्यन्ते विघ्नहेतवः । । ११ ।\nअन्वेष्टि च परं९ ब्रह्म स्वशरीरं समास्थितम् ।\nकृत्वैक्यं१० प्राणमनसामिन्द्रियाणां विनिग्रहात् । । १२ ।।\n- - - - - - - - -- - -\n१ अक्षर क्षरमेव - क., ह्यक्षरंक्षरमेव - ख.  २ अक्षर - क., त्वमक्षरं तत्क्षरं? - ख. । ३ अक्षरश्च - क. ख. । ४ इति - क. ख. । ५ स्वभ्यस्तमासनं - ख. । ६ नित्यमों क. । ७ पितिथाक्षश्च - क. क., पतिताक्षश्च - ख.। ८ मानसो - क. । ९ परमं - ख । १० कृत्वैको - क. ख. ।\n- - - - - - - - -- - -"
  },
  {
    "text": "957\nसर्वभावपरित्यागान्मोक्षमाप्नोत्यसंशयम् ।\nप्रत्याहाररतं कृत्वा सर्वमिन्द्रियगोचरम् । । १३ । ।\nततो युञ्जति निर्द्वन्द्वो मनस्सन्धानमाचरन् ।\nसर्वं मनसि संस्थाप्य परं तत्त्वं निरूपयेत् । । १४। ।\nअथैश्वर्यगतां सिद्धिं ध्यायन्नष्टविधां यदा ।\nपश्यते योगसंसिद्ध्या तदा योगी प्रकीर्त्यते । । १५ । ।\nब्रह्मसोमादिकान्११ देवान् यदा युक्तः प्रपश्यति ।\nयोगिभिः कथ्यते ह्येषा सिद्धिर्योगविकारजा ।। १६ ।।\nमनसा योगिनां सिद्धिः साख्यास्तत्त्वविनिश्चयात्१२ ।\nन विशेषोस्ति योगानां१३ मुक्त्वा माहेश्वरं१४ विधिम् । । १७।।\nयोगिनो ध्यानसंसिद्धिं सांख्यास्तत्त्वविनिश्चयम् ।\nअविभिन्नावुभावेतौ ध्यानतत्त्वार्थनिश्चयौ१५ । । १८ । ।\nसर्वबन्धपरिभ्रष्टः सङ्गदोषविवर्जितः ।\nरागमोहादिसंत्यक्तो मुक्त इत्यभिधीयते । । १९ । ।\nशब्दादीन् विषयान् युक्तो न ध्यायन्वेत्ति वै यदा ।\nअसकृद् योगसंसिद्ध्या तदा पश्यति तत्परम् । ।8.178.२ ० । ।\nमृत्युजन्मभयोद्विग्नः सङ्गदोषविवर्जितः ।\nअरण्ये मौनमाधाय ध्यायेदोङ्कारमक्षरम् ।। २१ । ।\nवेदादौ यः स्वरः प्रोक्तो वेदान्ते च प्रतिष्ठितः\nतस्य प्रकृतिलीनस्य१६ यः परः स महान् स्मृतः ।।२ २ ।।\nत्रिसंस्थानं त्रिमात्रं च त्रिब्रह्म त्र्यक्षरं तथा१७ ।\nमात्राहीनं समात्रं च यो विद्यात् स विमुच्यते ।। २३ । ।\nनाग्निस्तत्र न वायुश्च न सोमो न दिवाकरः ।\nप्रभवन्ति महेशाने ईश्वरे त्रिविकल्पिते । ।२४।।\n- - - - - - - - -- - -\n११ ब्रह्मसोमादयो - क. ख. ' । पे सख्याना गुणवर्जिता - ख. । १३ योगिनां न विशेषोस्ति (?), योगिनां - क. ख. । १४ माहेश्वरी - क. ख. ।  १५ निश्चितौ - क. ख. । १६ प्रकृतिहीनस्य - खः । १७ तदा  क\n- - - - - - - - -- - -\n958\nओङ्कारः१८ परमं तत्त्वमात्मा ब्रह्म च कीर्त्यते ।\nक्षेत्रज्ञैरात्मसंबोधाद्योगिभिः सूक्ष्मदर्शनात् । ।२५।।\nएवमेव सदा ध्यायन् मन आत्मनि योजयेत् ।\nईश्वरं प्राप्नुते योगी यमवाप्य विमुच्यते । ।२६। ।\nइन्द्रियाणि तु सर्वाणि शब्दरूपादिनिग्रहात्१९ ।\nविदित्वा कर्मजान् हन्ति योगी दोषानशेषतः२० । ।२७। ।\nध्यानशक्त्या ततः शुद्धः सर्वजिन्मोक्षमाप्नुते ।\nयुञ्जन् प्रतिदिनं व्यास षड्मासाद् योगमाप्नुते ।।२८।।\nपश्यते च परं ब्रह्म येन मुच्येत बन्धनात् ।\nतमात्मानं परं ज्ञात्वा योगशक्त्या महामुनिः ।\nपरमैश्वर्यसंयुक्त अमृतं२१ पदमाप्नुयात्२२ । ।२९ । ।\nइति स्कन्दपुराणे पाशुपतयोगवर्णने ध्यानविधौ पञ्चमः२३ अष्टसप्तत्युत्तर- शततमोध्यायः"
  },
  {
    "text": "सनत्कुमार उवाच\nअन्तःकरणसंसिद्धो यो महान् कथितो मया ।\nपञ्च कर्मेन्द्रियाण्यत्र पञ्च बुद्धीन्द्रियाणि च । । १ ।।\nपञ्चभूतं मनश्चात्र विकाराः षोडश स्मृताः ।\nमहान् बुद्धिरहङ्कारस्तन्मात्राणि च१ पञ्च हि । ।२। ।\nइमाः प्रकृतयो व्यास देहमष्टौ समाश्रिताः ।\nतत्त्वानि तु२ चतुर्विशत्येतान्युक्तानि३ योगिभिः ।\nदेहमेभिरवष्टब्धं त्रैलोक्यव्यापिभिः स्थितम् ।।३ । ।\nनाभिमध्ये तु नाडीनां शतमेकं प्रतिष्ठितम् ।\nसर्वाङ्गेषु तु यास्त्वन्या जलान्नरसवाहिकाः४ ।।४। ।\n- - - - - - - - -- - -\n१८ ओङ्कारं - ख. । १९ शब्दस्पर्शादोनिग्रहात् - (?) । २० यो गदोवानशेषतः - क. ख. । २१. ..ममृतं - ख.। २२ तदवाप्नुयात् - ख. । २३ ध्यानविधौ (?) । २४ अष्टषष्ट्युत्तर - क. ।"
  },
  {
    "text": "१ तु - क. । २ च - ख । ३. .देतान्युक्तानि - क. ख. । ६ रसवाहिनः - क., रसवाहिनी - ख. ।\n- - - - - - - - -- - -"
  },
  {
    "text": "959\nतासां त्रिंशत् सहस्राणि व्यानस्रोतसि५ संस्थिताः ।\nउदानस्यापरा नाड्यो६ ब्रह्ममूर्ध्नि प्रतिष्ठिताः । ।५। ।\nचक्रनाभी समाश्रित्य७ भूतसंघातमास्थितम् ।\nतन्मध्ये तु गुणस्पृष्टः८ कर्मात्मा भूतमोहनः ।।६। ।\nनक्षत्रोद्योतसंकाशो ज्योत्स्ना पुञ्जनिभः प्रभः९ ।\nविघातजननोन्येषां सूर्यायुतनिभः१० स्थितः ।।७। ।\nसंभूतोग्निरिवोत्पाती गिरिनीहारसन्निभः ।\nगुणस्थो भूतयोनिस्तु पुरुषः पञ्चविंशकः ।।८।।\nतस्यापि परतः शुद्धो महानग्निरिवोत्थितः ।\nअर्चिष्मान् सर्वतो दीप्तो निर्विकल्पो निरञ्जनः ।।९।।\nनिर्धूमाङ्गारसकाशो नविज्ञातागमक्रियः ।\nषड्विंशः पुरुषः सूक्ष्म ईश्वरः परमो विभुः ।। 8.179.१० ।।\nस एष११ कथितो व्यास परेषां परतः स्थितः ।\nमहादेवमिमं ज्ञात्वा मुच्यते तत्क्षणान्मुनिः ।।१ १ । ।\nगुणत्रयविकारस्थः कथितःपञ्चविंशकः ।\nभूयः संसरते तस्मादज्ञानेनैव मोहितः । । १ २। ।\nदेवमानुषतिर्यक्षु भ्राम्यते रागमोहितः ।\nषड्विंशकसमाधानात् सिद्धिस्तस्य विकारतः ।। १३ । ।\nक्रियाकार्यविनिर्मुक्तः सर्वज्ञः सर्वसृक्१२ प्रभुः ।\nपरमैश्वर्यसंपूर्णः कृतकृत्यो महेश्वरः ।।१४।।\nअजः स्वयम्भूः१३ षड्विंशः कूटस्थो ह्यचलो ध्रुवः ।\nततस्तत्त्वानि जायन्ते पुरुषश्च गुणैः सह ।। १५। ।\nतस्मिन्नेव च लीयन्ते षड्विंशे तु महेश्वरे ।\nविदित्वैनं महेशानं मुक्तिसिद्धिरवाप्यते ।।१ ६ ।।\n- - - - - - - - -- - -\n५ ध्यानस्रोतसि - ख. । ६ नाडी - क. ख. । ७ चक्रता?भीन्समाश्रित्य - क । ८ च गुणस्पृष्टः - ख । ९ पुञ्जनिभप्रभः - (?) । १० सूर्यातपनिभः - क. ख. । ११ एष स - ख. । १२ सर्वकृत् - क. । १३ स्वयम्भुः - क. । १४ विदित्वैकं - ख. ।\n- - - - - - - - -- - -\n960\nएतज्ज्ञात्वा न लिप्येत कर्मभिर्मोहबन्धनैः ।\nयथाग्निर्निर्दहेदन्ते भूतग्राममशेषतः । । १७ । ।\nषडविंशकपदार्थज्ञस्तथा कर्माणि निर्दहेत् ।\nसर्वव्यापि यथाकाशं सूक्ष्मं नैव तु लिप्यते । ।१ ८। ।\nषड्विंशकरतो योगी तथा पापैर्न लिप्यते ।\nषड्विंशात् परतो नास्ति तस्मात् तत्परमो१५ भवेत् । । १ ९। ।\nएकत्वं सह तेनैव त्यक्त्वा देहमवाप्नुते१६ ।\nब्रह्मविष्ण्वादिकं सर्व भूतग्राममशेषतः । ।8.179.२ ० ।।\nईश्वराज्जायते व्यास तस्मिन्नेव प्रलीयते ।\nनास्ति तस्मात् परो ह्यन्य१७स्तं विद्यात् सर्वतः स्थितम् ।।२१ ।।\nयमध्यात्मविदः सिद्धाः परमात्मेत्युपासते१८ ।\nस एष सर्वगो देवः षड्विंशः परमेश्वरः । ।२२ ।।\nप्राणोपानः१९ समानश्च उदानो व्यान एव च ।\nये पञ्चवायवो देहे तेषां निग्रहणं यतेत्२० ।। २३ । ।\nअपानञ्च समानञ्च कृत्वैकगतमादृतः२१ ।\nव्यानेन सहितं प्राणमुदाने सन्निवेशयेत् । ।२४।।\nनासाग्रे तु सकृत् प्राणं२२ प्रापयेद् योगशक्तितः ।\nभद्रां दृष्टिं समास्थाय२३ षड्विंशं चिन्तयेत्ततः । ।२५। ।\nमात्राः पञ्चदश प्रोक्ताः प्रथमं सन्धिबन्धनम् ।\nमात्रा विंशति विज्ञेयाः२४ पञ्चमःसन्धिविग्रहः । ।२६। ।\nनिश्शब्दे विजने देशे निरीहो विजितेन्द्रियः२५ ।\nस्वस्तिकं पद्मकं भद्रमथवा सिंहकच्छपौ२६ । । २७।।\nएकमासनमास्थाय षड्विंशं समनुस्मरन् ।\nसर्वाङ्गानि समाहृत्य निष्पन्दो ध्यानमाचरेत् । ।२८।।\n- - - - - - - - -- - -\n१५ परतमो - ख. । १६ त्यक्त्वा देहं स तैनैव सहैकत्वमवाप्नुते (?) । १७. त्स्तं - क. । १८ पर इत्युपसेवते - क. ख. । १९ प्राणापानौ - ख. । २० यतः - क । २१  मादितः (?) । २२ प्राणां (न्) - क. । २३ समादाय - ख. । २४ विंशतिका ज्ञेयाः - (?) । २५ विचलेन्द्रियः - ख. । २६ भद्रं सिंहं कच्छपमेव वा (?) ।\n- - - - - - - - -- - -\n961\nशनैः संचारयेद्वायुं नाडीभिः स्रोतसि स्थितम् ।\nतावत्तिष्ठेत युक्तात्मा ध्पानयोगाद् गतस्पृहः । ।२९।।\nसोममण्डलसंकाशं यावत् पश्येद्धृदि स्थितम् ।\nज्योतिर्देहाश्रितं दृष्ट्वा योगैश्वर्यं२७ प्रवर्तते । । 8.179.३० ।।\nतत एवं सदाभ्यासाद् योगसिद्धिप्रवर्तनात् ।\nत्रिकालविषयं ज्ञानं प्रत्यक्षं योगिनो भवेद् । ।३ १ । ।\nव्याधयो नाविशन्त्येनं न च दुःखान्वितो भवेत् ।\nस्वदेहस्य च सौगन्ध्यं वपुर्दिव्यं च जायते । ।३ २ ।।\nअमोघञ्च वचस्तस्य शापानुग्रहकारितम् ।\nप्रत्यवायो न चैवास्य भवेत् कर्मनिबन्धनः । । ३३ ।।\nसर्वविद्याविदां व्यास यतीनां व्रतचारिणाम्२८ ।\nतपस्विनां च विप्राणां योगी श्रेष्ठ उदाहृतः ।। ३४। ।\nनान्यथा मुच्यते जन्तुः संसारात् तमसः२९ परात्३० ।\nषड्विंशकपरिज्ञानं मुक्त्वा योगनिबन्धनम् । ।३ ५ ।।\nषडङ्गेन तु योगेन तथा पञ्चविधेन च ।\nजित्वा ह्यष्टप्रकारन्तु३१ आसनानां निबन्धनम् ।।३ ६।।\nमात्रोत्कर्षेण जित्वा च प्राणायामं चतुर्विधम् ।\nतन्मात्राणीन्द्रियैर्जित्त्वा विषयैरिन्द्रियाणि च । ।३७।। अहङ्कारभयायासक्रोधलोभविवर्जितः ।\nविमत्सरोथ निःसङ्गो निःस्नेहो निःस्पृहस्तथा । । ३८। ।\nयोगास्पदं समाधाय३२ पूर्वोक्तं गुणवर्जितम्३३ ।\nध्यायीत हृदि तं देवं विश्वं विश्वेश्वरं विभुम् ।।३ ९। ।\nअनादिनिधनं शान्तं त्रैगुण्यपरिवर्जितम् ।\nतालौ जिह्वां समाधाय दन्तैर्दन्तान् न च स्पृशन्३४ । ।8.179.४० ।।\n- - - - - - - - -- - -\n२७ योगी स्वैरं (?) । २८ ब्रह्मचारिणाम् - ख.। २९ तपसः - क. । ३० पुरान् - क. । ३१ पञ्चप्रकारन्तु - ख.। ३२ समादाय - ध. । ३३ गुणवर्जितः - ख. । ३४ न चास्पृशन् - क., निवास्पृशन् - ख. ।\n- - - - - - - - -- - -\n962\nइन्द्रियाणि मनश्चैव परमात्मनि योजयेत्३५ ।\nकृत्वा मनसि तत्सर्वं प्राणापानौ निरुद्ध्य च । ।४१ । ।\nओङ्कारं त्वसकृद् ध्यायन् संहृत्याङ्गानि कूर्मवत् ।\nशरीरं सर्वमापूर्य विक्षिपेत् सर्वमात्मनि३६ । ।४२।।\nतत्संहृत्य मुनिर्भूयो व्यापि भूतं प्रविस्तृतम् ।\nनाडीवायुप्रचारेण भूयोभूयस्तथारभेत्३७ । ।४३ । ।\nस पूर्वापररात्रे तु सात्विकं३८ चेत३९ उच्यते ।\nमध्याह्ने चापराह्णे च कृष्णं४० ध्यायीत तामसम् । ।४४।।\nसन्ध्ययोरुभयोर्नित्यं राजसं ध्यानमाचरेत् ।\nतैजसं सर्वतश्चापि ध्यानादेव जयेद् गुणान्४१ ।।४५ ।।\nसदैवं ध्ययतो व्यास तदैश्वर्यं प्रवर्तते ।\nयेन षड्विंशकं बुद्ध्वा हृदयस्थं महेश्वरम् ।।४६।।\nस्वेच्छया स्वतनुं त्यक्त्वा तस्मिन्नेव प्रलीयते ।\nपरमात्मा परं ब्रह्म कारणं पुरुषो महान् ।।४७। ।\nईश्वरो निर्गुणो भोक्ता षड्विंशः समुदाहतः ।\nयच्चा४२ सत् सदसच्चैव भूतिभूतो विभुः परः ।।४८।।\nजागर्त्ति स्वपते भुंक्ते सन्तिष्ठति ददाति च ।\nस स्रष्टा स च संहर्ता गुणातीतो महेश्वरः । ।४९।।\nइत्येतत् कथितं सर्वं सर्वयोगनिदर्शनम् ।\nयोगं पाशुपतं तुभ्य४३ माद्यं४४ मोक्षगतिप्रदम् । ।8.179.५ ० ।।\nसर्वप्रसङ्गरहितं हरवक्त्रविनिःसृतम् ।\nसूक्ष्मं तत्परमं ज्ञानं प्रवक्ष्यामि तवानघ ।\nयस्य सम्यक् परिज्ञानाद् विज्ञेयं नापरं भवेत् । ।५१ । ।\nइति स्कन्दपुराणे पाशुपतयोगवर्णने ध्यानविधौ षष्ठः ऊनाशीत्युत्तर४५ शततमोध्यायः४६\n- - - - - - - - -- - -\n३५ योजयन् (?) । ३६ सर्वतो मनः - ख. । ३७ भवेत्  ख., चरेत् (?) ' ३८ सार्थिकं - क । ३९ श्वेत (? ) । ४० कृत्स्नं - ख । ४१ गुणं - ख. । ४२ यच्च (?) । ४३ गुह्यं (?) । ४४. मद्य (?), मया (?) । ४५ ऊनसप्तत्युत्तर - क । ४६  १६९ - क., २२७ - ख. ।\n- - - - - - - - -- - -"
  },
  {
    "text": "963\nसनत्कुमार उवाच\nब्रह्माद्या देवता व्यास दक्षयज्ञवधे पुरा ।\nशङ्करं शरणं१ जग्मुर्वीरभद्रभयार्दिताः । ।१ । ।\nगणेन्द्रेणाभियुक्तास्तु२ भस्मकूटानि भेजिरे ।\nयदा भस्म प्रविष्टास्ते३ तेजः शाङ्करमुत्तमम्४ ।।२। ।\nअभवंस्ते तदा रौद्राः५ पशवो दीक्षिता इव ।\nभस्माभसितगात्राणां६ शङ्करव्रतचारिणाम् । ।३ ।।\nस्वं योगं प्रददौ तेषां तदा देव उमापतिः ।\nसर्वासां७ मोक्षविद्यानां यत्तत्त्वमतिरिच्यते ।।४।।\nहिरण्यगर्भप्रमुखैर्योगिमुख्यैः प्रवर्तितः८ ।\nयो योगः सकलो व्यास कृच्छ्रोपायप्रसाधनः ।।५।।\nजन्मान्तरसहस्रैस्तु तमभ्यस्य महामुने ।\nप्राप्नुवन्ति परं९ ज्योतिर्योगैश्वर्यमथापि वा ।\nयोयं भगवता साक्षाद् योगो माहेश्वरः परः । ।६। ।\nतत्त्वतः कथितस्तेषां प्रपन्नानां१० दिवौकसाम् ।\nअस्य सम्यक् परिज्ञानादनेनैव तु जन्मना । ।७। ।\nव्रतं पाशुपतं प्राप्य षड्मासाज् ज्ञानमाप्नुते ।\nयोगैश्वर्यं महद्११ व्यास यदवाप्य विमुच्यते ।।८। ।\nसर्वधर्मं बहिः कृत्वा निष्कलस्य प्रभावतः ।\nदीक्षां पाशुपतीं प्राप्य तं१२ विशन्ति महेश्वरम् । ।९।।\nसर्वज्ञानसमायुक्तं तपोधर्मबहिष्कृतम्१३ ।\nभस्मसाधनमात्रं तु शिवेन कथितं व्रतम् ।।8.180.१ ० ।।\nपापिष्ठा धर्मवन्तो वा भक्ताः केवलमीश्वरम् ।\nसेवनाद्यस्य मुच्यन्ते तन्निबोध महाव्रतम् ।। ११ । ।\n- - - - - - - - -- - -"
  },
  {
    "text": "१ शरणं शङ्करं - ख- । २ संयुक्ता - ख- । ३ प्रदीप्तास्ते - ख. । ४ शङ्करमुत्तमम् - क. ख. । ५ महारौद्राः - क । ६ भषित (रुषितः )गात्राणां - ख. । ७ सर्वेषां - क. ।८ प्रवर्तितम् - क । ९ यदि - ख. । १० प्रसन्नानां - क. । ११ गतो - ख. । १२ मा - क. ख. । १३ तयोधर्मविहिष्कृतम् - क. ।\n- - - - - - - - -- - -"
  },
  {
    "text": "964\nअधर्मं न विना धर्मो न च धर्मं विनाशुभम् ।\nएतौ परस्परं बद्धौ त्यक्त्वा तस्मादिमावुभौ ।।१ २ । ।\nधर्माधर्मपरित्यक्तश्चरेत् पाशुपतं व्रतम् ।\nततो योगमिमं प्राप्य महदैश्वर्यमाप्नुते ।। १३ ।।\nभस्मग्रहणमात्रात्तु१४ ते सर्वबन्धप्रमोचनम् ।\nमुच्यते स्पृष्टमात्रस्तु१५ ब्रह्मपूतेन१६ भस्मना ।। १४। ।\nदहेत् सोमकृतं वह्निरीश्वरं चानलं१७ विदुः ।\nकृताकृत दहत्यग्निर्भूयः१८ सोमसमागतः१९ । । १ ५। ।\nभस्मना मोचिताः सर्वे ब्रह्माद्या अभिमानिनः ।\nभस्मनस्तेजसो२० वीर्यं भस्म पावनमीश्वरम् ।।१ ६।।\nआत्मानमुद्धरेद्२१ व्यास२२ यः स्नानं भस्मना चरेत्२३ ।\nभस्मना शिवयोगेन मुच्यते पाशबन्धनात्२४ ।।१७।।\nप्रभवन्ति सुराः सोमात् पितरो वह्निसंभवाः२५ ।\nवह्निसोमात्मकं२६ तस्माज्जगत्सर्वं प्रतिष्ठितम् । ।१८। ।\nईश्वरोग्निश्च सोमश्च भस्म तत्तेज उच्यते ।\nतेजसा तस्य संस्पृष्टो मुच्यते जन्मना२७ द्विज२८ ।।१ ९ ।।\nसांख्यं विद्यास्तपश्चैव त्यक्त्वा धर्मांश्च वैदिकान् ।\nकेवलं भस्मसंस्नानात् पूतो गच्छति तत्पदम् ।।8.180.२ ० ।।\nविषयानपि संसेव्य बह्वधर्मरतोपि सन्२९ ।\nपश्चाद् भक्तिपरः शम्भोर्भस्मनैव३० हि शुद्ध्यति ।।२ १ ।।\nआत्मानं यः३१ पशुं कृत्वा महादेवं हुताशनम् ।\nदीक्षितो ब्रह्मभस्मभ्यां शिवयाजी मुनिर्भवेत३२ ।।२२।।\n- - - - - - - - -- - -\n१४ तन्मात्रात् - क, तन्मात्रं - ख., तन्मात्रं तु  (?)। १५ सृष्टमात्रस्तु  - ख । १६ ब्रह्मभूतेन (?) । १७ चालनं  क । १८ दहेदग्निर्भूयः - ख । १९ समागतम् - क । २० भस्मसस्तेजसो - क. ख । २१ शङ्करे - ख. । २२ न्यस्य - ख. । ३ भस्मसाचरेत् - क ख । २४ पापबन्धनात्  क। २५ संभवान् (त्) - क । २६ वह्नीसोमात्मकं - क ख । २७ जन्मनो  ? । २८ द्विजं - क, द्विजः - ख. । २९ सः - ख. । ३० भस्मसैव - क ख. । ३१ स - ख. । ३२ शिवयाजिमुनिर्भवेत् - क., शिवयोगी ? ।\n- - - - - - - - -- - -"
  },
  {
    "text": "965\nशीघ्रमेव परं योगं प्राप्य मुच्येत३३ बन्धनात् ।\nएवं व्रतमनुप्राप्य भूत्वा पाशुपतो मुनिः । । २३ ।।\nइदं३४ माहेश्वरं ज्ञानं३५ गुह्यं परममभ्यसेत् ।\nज्ञेयं ज्ञानं तथा ज्ञाता त्रयं देहे यथा स्थितम् ।। २४।।\nआत्मा यश्च यथा चासौ स्थानत्रयसमास्थितः ।\nनाडीषु च यथा ह्यात्मा आत्मन्येवानुतिष्ठति ।।२५।।\nसर्वतः सर्वभूतेषु निगूढस्तिष्ठते यथा ।\nपयसीव घृतं व्यास यं विदित्वा विमुच्यते । ।२६।।\nन स वेत्तुं३६ विना ज्ञानं शक्य आत्मा कथञ्चन ।\nरूपशब्दरसातीतं कस्तं वेत्ति महेश्वरम् ।।२७। ।\nतथा ह्यहं महाभाग प्रसादात्३७ त्र्यम्बकस्य तु ।\nआत्मज्ञानषरोपायं कथयामि तवानघ । । २८। ।\nसर्वमेव तमः पूर्वमिदमासीज्जगत् किल ।\nन देवा नानिलो न द्यौर्न सूर्यश्चन्द्रमा न च३८ ।। २९।।\nन किञ्चित् सर्वथा भूतं३९ दृश्यते जगति स्थितम ।\nशुद्धं विमलमाभाति अक्षरं परमैश्वरम् । ।8.180.३ ० ।।\nसर्वभावगुणातीतं निर्विकल्पं निरञ्जनम् ।\nबहिरन्तश्चरं दीप्तमविनाशि वरं ध्रुवम् ।\nयथा तदक्षरं ब्रह्म प्रोच्यमानं तथा शृणु । । ३१ । ।\nओमित्येकाक्षरं पूर्वं क्षरं तस्माद्विनिर्गतम् ।\nव्यक्षरश्च त्रिमात्रश्च ओङ्कारो ब्रह्म शब्द्यते । ।३ २ ।।\nअकारे तत्र विष्णुस्तु उकारे तु पितामहः ।\nमकारे भगवानीशो मात्रायां प्रकृतिः स्मृता ।।३ ३ । ।\nब्रह्मविष्णू४० स्मृतौ यौ तौ४१ देवावीश्वरनिर्गतौ ।\nप्रकृतिस्त्रीत्वमास्थाय४२ नित्यन्तावीशपार्श्वगौ४३ । ।३४।।\n- - - - - - - - -- - -\n३३ मुच्यति - क. ख- । ३४ इम - क. ख । ३५ योग (?) । ३६ नावसेतु - ख । ३७ महाया (यो)गप्रसादात् - ख. । ३८ न सूर्यो न च चन्द्रमाः (?) । ३९ सर्वभूतानां - ख. । ४० ब्रह्माविष्णु - क. ख. । ४१ तु - क ख. । ४२ प्रकृतिः स्त्रीत्वमास्थाय ( ?) । ४३ तिष्ठन्तावीशपार्श्वगौ - क. ।\n- - - - - - - - -- - -"
  },
  {
    "text": "966\nपत्नीरूपेण सा शम्भुं भजते प्रकृतिस्सदा ।\nक्षरन्तु प्रकृतिः४४ ख्याताक्षरस्तु४५ स्वयमीश्वरः ।।३ ५।।\nईश्वरान्निर्गता सा हि प्रकृतिर्गुणबन्धना ।\nतस्याः स्रष्टा महादेवो यतो विष्णुपितामहौ ।। ३ ६।।\nप्रजापती समुत्पन्नौ गुणत्रयनिबन्धनौ ।\nतावाक्रम्य महेशस्तु प्रकृतिस्थौ गुणात्मकौ ।।३७।।\nमकारस्थो विभुर्भूत्वा भुंक्ते संचरते च हि ।\nगुह्यमेतत् परं ज्ञात्वा मयोक्तं तत्त्वमक्षरम्४६ ।।३८। ।\nयेनैव४७ घ्यानिना४८ व्यास ईश्वरोसौ विकल्पितः ।\nस तमाविश्य मुक्तात्मा कृतार्थो जायते मुनिः४९ । ।३९। ।\nनैनं जानन्त्यमार्गस्थास्तर्कहेतुपरायणाः ।\nभोक्तारं प्रकृतेरीशं परं षड्विंशसंज्ञितम् ।।8.180.४० । ।\nओङ्कारः५० प्रकृतिर्नित्यं तन्मध्ये चेश्वरः स्थितः५१ ।\nपयोमध्ये यथा व्यास सर्पिरन्तर्गतं स्थितम् ।।४१ ।।\nओङ्कारं ध्यायता येन५२ अतीत्य प्रकृतिं मुने ।\nईश्वरोसौ महान् विन्नः स मुक्तः पशुबन्धनैः ।।४२।।\nईश्वरी प्रकृतिः ख्याता गुणबन्धाद्विमोहनी ।\nब्रह्मत्वाद् बृंहणी ह्ये षा विष्णुत्वाद्विभवाश्रिता । ।४३।।\nप्रसादादीश्वरस्यैषा प्रकृतिस्त्रिगुणात्मिका५३ ।\nसाभिमाना भवस्रष्ट्री५४ भोक्ता तस्या महेश्वरः ।।४४। ।\nअष्टबाहुस्त्रिपादा च पञ्चदेहमुखी तथो ।\nद्विनेत्रा पंचकर्मस्था सप्तवाजिरथोपगा ।।४५।\nजगन्माता स्मृता ह्येषा गुणत्रयविकारजा ।\nउभे शुभाशुभे तस्यान्५५ विद्याविद्ये तथा ह्युभे । ।४६। ।\n- - - - - - - - -- - -"
  },
  {
    "text": "४४ अक्षरप्रकृतिः - ख. । ४५ क्षरस्तु - ख. । ४६ तत्त्वतोक्षरः - क । ४७ येनैवं - ख । ४८ ध्यानिनो- ख. । ४९ मुने  (?) । ५० ओङ्कारं - ख. । ५१ चेश्वरं स्थितं - क. । ५२ ध्यायतो नित्यं - ख. । १३ स्त्री गुणात्मिका - क, । ५४. .भवत् स्रष्टी - क., .. .भवत्स्रष्टा - ख. । ५५ तस्यां - ख. ।\n- - - - - - - - -- - -"
  },
  {
    "text": "967\nउद्भवोथ प्रणाशश्च क्रियानुष्ठानमेव च ।\nनिमित्तं चाभवद्योनिर्भावाः५६ संक्षेपतस्त्वमी ।।४७ ।।\nईश्वराज्जात ओङ्कारः५७ स च तस्मिन् प्रतिष्ठितः ।\nओङ्कारात् सर्वमुत्पन्नमाब्रह्मभवनं५८ जगत् ।।४८ ।।\nअतः कृत्वा महाभाग योगिनः कपिलादयः ।\nओङ्कारं परमं५९ ब्रह्म निर्विकल्पमुपासते । ।४९। ।\nस एव सर्वगो ह्यात्मा कारणं च स एव तु ।\nएवं प्रकृतिभूतौ तावोङ्कारप्रभवौ स्थितौ६० । ।8.180.५ ० । ।\nईशभोज्यौ गुणात्मानौ ज्ञात्त्वा विष्णुपितामहौ ।\nतत्सृष्टौ वेदयज्ञाख्यौ मुक्त्वा धर्मनिबन्धनौ ।।५ १ । ।\nमहामोहौ तमोनिष्ठौ६१ विषयासङ्गसंयुतौ ।\nसत्वपूर्वौ रजोमध्यौ सुखदुःखान्वितौ सदा । ।५२। ।\nसंसारभ्रमणौ मूढौ सर्वानित्यसमायुतौ ।\nईश्वरेप्सुर्भवेद्विद्वान् ध्यायोगपरायणः । ।५३ । ।\nतस्मात् प्रकृतिरुत्पन्ना तस्मिन्नेव प्रणश्यति ।\nयेनासावीश्वरो विन्नो योगेनात्मनि संस्थितः ।\nप्रकृतिस्तं न बध्नाति मुच्यते च भवार्णवात् । ।५४। ।\nइति स्कन्दपुराणे पाशुपतयोगवर्णने ध्यानविधौ सप्तमः अशीत्युत्तरशततमोध्यायः"
  },
  {
    "text": "सनत्कुमार उवाच\nआत्मा सूक्ष्मो मनोबुद्धिरहङ्कारो गुणास्तथा ।\nभूतानीन्द्रियसंघातस्तन्मात्राणि दशानिलाः१ ।।१ ।।\nविभक्ताः क्रमशो देहे विभागेन यथाश्रयम् ।\nस्वप्नजाग्रत्सुषुप्तेषु२ स्थानेषु त्रिषु सुव्रत ।।२ । ।\n- - - - - - - - -- - -\n५६ चारुव द्योनिर्भावाः - क, चाभवेद्योनिर्भावाः - ख. । ५७ जायतोङ्कारः - क. । ५८ भुवनं (?) । ५९ ओङ्कारपरमं - क. ख. । ६० प्रभवास्थितौ - क. ख. । ६१ महामोहतमोनिष्ठौ (?) । १ स्तन्मात्रण्यनिलात्मकः - ख. । २ जाग्रत्स्वप्नसुषुप्तेषु (?) ।\nसुषुप्तेषु ()\n- - - - - - - - -- - -"
  }
]